tests/testfiles/hierarchy_ift/hierarchy_ift.v
module S(a, a_t, b, b_t, c, c_t);
    input a,b;
    input [31:0] a_t, b_t;
    output c;
    output [31:0] c_t;

    assign c = a & b;
    assign c_t = ((a > 0 ? b_t : 0) | (b > 0 ? a_t : 0) | (a_t & b_t ));
endmodule


module M(a, a_t, b, b_t, c, c_t);
    input a,b;
    input [31:0] a_t, b_t;
    wire d;
    wire [31:0] d_t;
    wire e, f;
    wire [31:0] e_t, f_t;
    output c;
    output [31:0] c_t;
    
    S s1(.a(e),
        .a_t(e_t),
        .b(b), 
        .b_t(b_t), 
        .c(d), 
        .c_t(d_t));
    S s2(.a(f), 
        .a_t(f_t), 
        .b(d), 
        .b_t(d_t), 
        .c(c), 
        .c_t(c_t));
 
    assign e = a ^ b;
    assign e_t = a_t | b_t;
    assign f = a | b;
    assign f_t = ((a == 0 ? b_t : 0) | ( b == 0 ? a_t : 0) | (a_t & b_t)); 
 
endmodule

module hierarchy(a, a_t, b, b_t, c, c_t);
    input a,b;
    input [31:0] a_t, b_t;
    wire d;
    wire [31:0] d_t;
    output c;
    output [31:0] c_t;

    M m1(.a(a), .a_t(a_t), .b(b), .b_t(b_t), .c(d), .c_t(d_t));
    M m2(.a(a), .a_t(a_t), .b(d), .b_t(d_t), .c(c), .c_t(c_t));
endmodule

tests/testfiles/ift/hierarchy_ift_tb.v
module hierarchy_tb;
   reg a,b;
   wire c;
   reg [31:0] a_t,b_t;
   wire [31:0] c_t;

   reg [95:0] read_data [0:95];
   integer i, t;
   
   initial begin
      a = 0;
      b = 0;
      #8;
      a = 0;
      b = 1;
      #8;
      a = 1;
      b = 0;
      #8;
      a = 1;
      b = 1;
      #8;
   
   end

   hierarchy t1(.a(a), .a_t(a_t), .b(b), .b_t(b_t), .c(c), .c_t(c_t));
      
   initial begin
      $readmemb(`INPUT_FILE_NAME, read_data);
      for(i = 0; i<=15; i++) begin
      {a_t, b_t, t} =  read_data[i];
      #t;
      end
   end

   initial
      begin
         $dumpfile(`DUMP_FILE_NAME);
        $dumpvars(1);		//writing the vcd file
      end
      
   //initial
      //$monitor("At time %t, value = %h (%0d)", $time, a, b, c);

endmodule

tests/testfiles/ift/hierarchy_ift_test.vcd
$date
	Mon Jun 12 11:18:27 2023
$end
$version
	Icarus Verilog
$end
$timescale
	1s
$end
$scope module hierarchy_tb $end
$var wire 32 ! c_t [31:0] $end
$var wire 1 " c $end
$var reg 1 # a $end
$var reg 32 $ a_t [31:0] $end
$var reg 1 % b $end
$var reg 32 & b_t [31:0] $end
$var integer 32 ' i [31:0] $end
$var integer 32 ( t [31:0] $end
$upscope $end
$enddefinitions $end
#0
$dumpvars
b10 (
b0 '
b0 &
0%
b0 $
0#
0"
b0 !
$end
#2
b1 !
b1 &
b1 '
#4
b0 !
b10 $
b0 &
b10 '
#6
b1 !
b1 &
b11 '
#8
b0 !
1"
b0 $
b0 &
b100 '
1%
#10
b101 '
#12
b10 !
b10 $
b110 '
#14
b11 !
b1 &
b111 '
#16
b0 !
0"
b0 $
b0 &
b1000 '
0%
1#
#18
b1 !
b1 &
b1001 '
#20
b0 !
b10 $
b0 &
b1010 '
#22
b1 !
b1 &
b1011 '
#24
b0 !
b0 $
b0 &
b1100 '
1%
#26
b1 !
b1 &
b1101 '
#28
b10 !
b10 $
b0 &
b1110 '
#30
b11 !
b1 &
b1111 '
#32
b10000 '
