tests/testfiles/ift/flipFlops/aldff/aldff_ift.v
module m_0 (AD, AD_t, ALOAD, ALOAD_t, CLK, CLK_t, D, D_t, Q, Q_t);

parameter WIDTH = 2;
parameter CLK_POLARITY = 1'b1;
parameter ALOAD_POLARITY = 1'b1;

input CLK, ALOAD;
input [WIDTH-1:0] AD;
input [WIDTH-1:0] D;
input [31:0] AD_t;
input [31:0] D_t;
input [31:0] CLK_t;
input [31:0] ALOAD_t;
output reg [WIDTH-1:0] Q;
output reg [31:0] Q_t;
wire pos_clk = CLK == CLK_POLARITY;
wire pos_aload = ALOAD == ALOAD_POLARITY;

initial begin
    Q_t = 0;
end

always @(posedge pos_clk, posedge pos_aload) begin
	if (pos_aload) begin
		Q <= AD;
		Q_t <= (^D === 1'bx) ? 0 : ((D == ALOAD) ? (D_t | AD_t) : AD_t);
	end
	else begin
		Q <= D;
		Q_t <= (^D === 1'bx) ? 0 : ((D == ALOAD) ? (D_t | AD_t) : D_t);
	end
end

endmodule

tests/testfiles/ift/flipFlops/aldff/aldff_ift_tb.v
`timescale 1ns/1ps
module aldff_tb();
	reg [1:0] D;
	reg [1:0] AD;
	reg CLK;
	reg ALOAD;
	wire[1:0] Q;
	
	reg [31:0] D_t;
	reg [31:0] CLK_t = 0;
	reg [31:0] ALOAD_t;
	reg [31:0] AD_t;
	wire [31:0] Q_t;

	reg[95:0] read_data [0:7];
	integer i;

	m_0 d1(AD, AD_t, ALOAD, ALOAD_t, CLK, CLK_t, D, D_t, Q, Q_t);

	initial begin 
		$readmemb(`INPUT_FILE_NAME, read_data);
		for(i = 0; i<=7; i+=1) begin
		{AD_t, ALOAD_t, D_t} = read_data[i];
		 #40;
		 D <= 'b00;
		 AD <= 'b11;
		 #5;
		 ALOAD <= 1;
		 #5;
		 ALOAD <= 0;
		 #40;
		 D <= 'b01;
		 AD <= 'b1;
		 #5;
		 ALOAD <= 1;
		 #5;
		 ALOAD <= 0;
		 #40;
		 D <= 'b10;
		 AD <= 'b01;
		 #5;
		 ALOAD <= 1;
		 #5;
		 ALOAD <= 0;
		 #40;
		 D <= 'b11;
		 AD <= 'b00;
		 #5;
		 ALOAD <= 1;
		 #5;
		 ALOAD <= 0;
		 #40;
		end
		$finish;
	end

	initial begin
  		CLK=0;
     		forever #10 CLK = ~CLK;  
	end 

	initial
	begin
		$dumpfile(`DUMP_FILE_NAME);
		//$dumpfile("../../examples/flipFlops/aldff/aldffExport.vcd");
		$dumpvars(1);		//writing the vcd file
	end
 	
endmodule

tests/testfiles/ift/flipFlops/aldff/aldff_ift.vcd
$date
	Mon Feb  5 16:42:00 2024
$end
$version
	Icarus Verilog
$end
$timescale
	1ps
$end
$scope module aldff_tb $end
$var wire 32 ! Q_t [31:0] $end
$var wire 2 " Q [1:0] $end
$var reg 2 # AD [1:0] $end
$var reg 32 $ AD_t [31:0] $end
$var reg 1 % ALOAD $end
$var reg 32 & ALOAD_t [31:0] $end
$var reg 1 ' CLK $end
$var reg 32 ( CLK_t [31:0] $end
$var reg 2 ) D [1:0] $end
$var reg 32 * D_t [31:0] $end
$var integer 32 + i [31:0] $end
$upscope $end
$enddefinitions $end
$comment Show the parameter values. $end
$dumpall
$end
#0
$dumpvars
b0 +
b100 *
bx )
b0 (
0'
b10 &
x%
b1 $
bx #
bx "
b0 !
$end
#10000
1'
#20000
0'
#30000
1'
#40000
b11 #
b0 )
0'
#45000
b1 !
b11 "
1%
#50000
0%
1'
#60000
0'
#70000
b101 !
b0 "
1'
#80000
0'
#90000
b1 #
b1 )
1'
#95000
b1 "
1%
#100000
0%
0'
#110000
b100 !
1'
#120000
0'
#130000
1'
#140000
b10 )
0'
#145000
b1 !
1%
#150000
0%
1'
#160000
0'
#170000
b100 !
b10 "
1'
#180000
0'
#190000
b0 #
b11 )
1'
#195000
b1 !
b0 "
1%
#200000
0%
0'
#210000
b100 !
b11 "
1'
#220000
0'
#230000
1'
#240000
0'
b0 &
b0 *
b1 +
#250000
b0 !
1'
#260000
0'
#270000
1'
#280000
b11 #
b0 )
0'
#285000
b1 !
1%
#290000
0%
1'
#300000
0'
#310000
b0 "
1'
#320000
0'
#330000
b1 #
b1 )
1'
#335000
b1 "
1%
#340000
0%
0'
#350000
b0 !
1'
#360000
0'
#370000
1'
#380000
b10 )
0'
#385000
b1 !
1%
#390000
0%
1'
#400000
0'
#410000
b0 !
b10 "
1'
#420000
0'
#430000
b0 #
b11 )
1'
#435000
b1 !
b0 "
1%
#440000
0%
0'
#450000
b0 !
b11 "
1'
#460000
0'
#470000
1'
#480000
0'
b10 &
b10 +
#490000
1'
#500000
0'
#510000
1'
#520000
b11 #
b0 )
0'
#525000
b1 !
1%
#530000
0%
1'
#540000
0'
#550000
b0 "
1'
#560000
0'
#570000
b1 #
b1 )
1'
#575000
b1 "
1%
#580000
0%
0'
#590000
b0 !
1'
#600000
0'
#610000
1'
#620000
b10 )
0'
#625000
b1 !
1%
#630000
0%
1'
#640000
0'
#650000
b0 !
b10 "
1'
#660000
0'
#670000
b0 #
b11 )
1'
#675000
b1 !
b0 "
1%
#680000
0%
0'
#690000
b0 !
b11 "
1'
#700000
0'
#710000
1'
#720000
0'
b0 &
b100 *
b11 +
#730000
b100 !
1'
#740000
0'
#750000
1'
#760000
b11 #
b0 )
0'
#765000
b1 !
1%
#770000
0%
1'
#780000
0'
#790000
b101 !
b0 "
1'
#800000
0'
#810000
b1 #
b1 )
1'
#815000
b1 "
1%
#820000
0%
0'
#830000
b100 !
1'
#840000
0'
#850000
1'
#860000
b10 )
0'
#865000
b1 !
1%
#870000
0%
1'
#880000
0'
#890000
b100 !
b10 "
1'
#900000
0'
#910000
b0 #
b11 )
1'
#915000
b1 !
b0 "
1%
#920000
0%
0'
#930000
b100 !
b11 "
1'
#940000
0'
#950000
1'
#960000
0'
b0 $
b10 &
b0 *
b100 +
#970000
b0 !
1'
#980000
0'
#990000
1'
#1000000
b11 #
b0 )
0'
#1005000
1%
#1010000
0%
1'
#1020000
0'
#1030000
b0 "
1'
#1040000
0'
#1050000
b1 #
b1 )
1'
#1055000
b1 "
1%
#1060000
0%
0'
#1070000
1'
#1080000
0'
#1090000
1'
#1100000
b10 )
0'
#1105000
1%
#1110000
0%
1'
#1120000
0'
#1130000
b10 "
1'
#1140000
0'
#1150000
b0 #
b11 )
1'
#1155000
b0 "
1%
#1160000
0%
0'
#1170000
b11 "
1'
#1180000
0'
#1190000
1'
#1200000
0'
b100 *
b101 +
#1210000
b100 !
1'
#1220000
0'
#1230000
1'
#1240000
b11 #
b0 )
0'
#1245000
b0 !
1%
#1250000
0%
1'
#1260000
0'
#1270000
b100 !
b0 "
1'
#1280000
0'
#1290000
b1 #
b1 )
1'
#1295000
b1 "
1%
#1300000
0%
0'
#1310000
1'
#1320000
0'
#1330000
1'
#1340000
b10 )
0'
#1345000
b0 !
1%
#1350000
0%
1'
#1360000
0'
#1370000
b100 !
b10 "
1'
#1380000
0'
#1390000
b0 #
b11 )
1'
#1395000
b0 !
b0 "
1%
#1400000
0%
0'
#1410000
b100 !
b11 "
1'
#1420000
0'
#1430000
1'
#1440000
0'
b0 &
b110 +
#1450000
1'
#1460000
0'
#1470000
1'
#1480000
b11 #
b0 )
0'
#1485000
b0 !
1%
#1490000
0%
1'
#1500000
0'
#1510000
b100 !
b0 "
1'
#1520000
0'
#1530000
b1 #
b1 )
1'
#1535000
b1 "
1%
#1540000
0%
0'
#1550000
1'
#1560000
0'
#1570000
1'
#1580000
b10 )
0'
#1585000
b0 !
1%
#1590000
0%
1'
#1600000
0'
#1610000
b100 !
b10 "
1'
#1620000
0'
#1630000
b0 #
b11 )
1'
#1635000
b0 !
b0 "
1%
#1640000
0%
0'
#1650000
b100 !
b11 "
1'
#1660000
0'
#1670000
1'
#1680000
0'
b0 *
b111 +
#1690000
b0 !
1'
#1700000
0'
#1710000
1'
#1720000
b11 #
b0 )
0'
#1725000
1%
#1730000
0%
1'
#1740000
0'
#1750000
b0 "
1'
#1760000
0'
#1770000
b1 #
b1 )
1'
#1775000
b1 "
1%
#1780000
0%
0'
#1790000
1'
#1800000
0'
#1810000
1'
#1820000
b10 )
0'
#1825000
1%
#1830000
0%
1'
#1840000
0'
#1850000
b10 "
1'
#1860000
0'
#1870000
b0 #
b11 )
1'
#1875000
b0 "
1%
#1880000
0%
0'
#1890000
b11 "
1'
#1900000
0'
#1910000
1'
#1920000
0'
b1000 +
