tests/testfiles/test_cells/pmux/pmux.v
/* Generated by Yosys 0.20 (git sha1 4fcb95ed087, clang  -fPIC -Os) */

(* dynports =  1  *)
(* src = "mux.v:1.1-16.10" *)
module m_0 (A, B, S, Y);
  (* src = "mux.v:5.23-5.24" *)
  input [1:0] A;
  wire [1:0] A;
  (* src = "mux.v:5.26-5.27" *)
  input [1:0] B;
  wire [1:0] B;
  (* src = "mux.v:6.11-6.12" *)
  input S;
  wire S;
  (* src = "mux.v:7.28-7.29" *)
  output [1:0] Y;
  wire [1:0] Y;
  function [1:0] _0_;
    input [1:0] a;
    input [1:0] b;
    input [0:0] s;
    (* full_case = 32'd1 *)
    (* parallel_case = 32'd1 *)
    (* src = "mux.v:10.13-10.14|mux.v:10.9-13.19" *)
    (* parallel_case *)
    casez (s)
      1'b1:
        _0_ = b[1:0];
      default:
        _0_ = a;
    endcase
  endfunction
  assign Y = _0_(A, B, S);
endmodule

tests/testfiles/test_cells/pmux/pmux_tb.v
`timescale 1us/100ns
module tb_SR();
	reg [1:0] A;
	reg [1:0] B;
	reg S;
	wire[1:0] Y;
	

	m_0 d1(.A(A),.B(B),.S(S),.Y(Y));

	initial begin 
		 #40;
		 A <= 'b00;
		 B <= 'b00;
		 S <= 'b1;
		 #5;
		 B <= 'b10;
		 #5;
		 B <= 'b11;
		 #40;
		 A <= 'b01;
		 B <= 'b00;
		 S <= 'b1;
		 #5;
		 B <= 'b10;
		 #5;
		 B <= 'b11;
		 #40;
		 A <= 'b11;
		 B <= 'b00;
		 S <= 'b1;
		 #5;
		 B <= 'b10;
		 #5;
		 B <= 'b11;
		 #40;
		 A <= 'b10;
		 B <= 'b00;
		 S <= 'b1;		 
		 #5;
		 B <= 'b10;
		 #5;
		 B <= 'b11;
		 #40;
		 A <= 'b00;
		 B <= 'b00;
		 S <= 'b0;
		 #5;
		 B <= 'b10;
		 #5;
		 B <= 'b11;
		 #40;
		 A <= 'b01;
		 B <= 'b00;
		 S <= 'b0;
		 #5;
		 B <= 'b10;
		 #5;
		 B <= 'b11;
		 #40;
		 A <= 'b11;
		 B <= 'b00;
		 S <= 'b0;
		 #5;
		 B <= 'b10;
		 #5;
		 B <= 'b11;
		 #40;
		 A <= 'b10;
		 B <= 'b00;
		 S <= 'b0;		 
		 #5;
		 B <= 'b10;
		 #5;
		 B <= 'b11;
		 #40;
		 $finish;
	end
	initial
	begin
		$dumpfile(`DUMP_FILE_NAME);
		//$dumpfile("pmux.vcd");
		$dumpvars(1);		//writing the vcd file
	end
 	
endmodule

tests/testfiles/test_cells/pmux/pmux.vcd
$date
	Tue Apr  4 23:26:22 2023
$end
$version
	Icarus Verilog
$end
$timescale
	100ns
$end
$scope module tb_SR $end
$var wire 2 ! Y [1:0] $end
$var reg 2 " A [1:0] $end
$var reg 2 # B [1:0] $end
$var reg 1 $ S $end
$upscope $end
$enddefinitions $end
#0
$dumpvars
x$
bx #
bx "
bx !
$end
#400
b0 !
1$
b0 #
b0 "
#450
b10 !
b10 #
#500
b11 !
b11 #
#900
b0 !
b0 #
b1 "
#950
b10 !
b10 #
#1000
b11 !
b11 #
#1400
b0 !
b0 #
b11 "
#1450
b10 !
b10 #
#1500
b11 !
b11 #
#1900
b0 !
b0 #
b10 "
#1950
b10 !
b10 #
#2000
b11 !
b11 #
#2400
b0 !
0$
b0 #
b0 "
#2450
b10 #
#2500
b11 #
#2900
b1 !
b0 #
b1 "
#2950
b10 #
#3000
b11 #
#3400
b11 !
b0 #
b11 "
#3450
b10 #
#3500
b11 #
#3900
b10 !
b0 #
b10 "
#3950
b10 #
#4000
b11 #
