tests/testfiles/test_cells/shift_ab_sign/shift_ab_sign.v
/* Generated by Yosys 0.20 (git sha1 4fcb95ed087, clang  -fPIC -Os) */

(* src = "shift.v:1.1-29.10" *)
module m_0(A, B, Y);
  (* src = "shift.v:9.25-9.26" *)
  input [1:0] A;
  wire [1:0] A;
  (* src = "shift.v:10.25-10.26" *)
  input [1:0] B;
  wire [1:0] B;
  (* src = "shift.v:11.26-11.27" *)
  output [1:0] Y;
  wire [1:0] Y;
  assign Y = $signed(B) < 0 ? $signed(A) << - B : $signed(A) >> B;
endmodule

tests/testfiles/test_cells/shift_b_sign/shift_b_sign_tb.v
`timescale 1ns/1ps
module tb_shift();
	reg [1:0] A;
	reg [1:0] B;
	wire[1:0] Y;

	m_0 d1(.A(A),.B(B),.Y(Y));


	initial begin 
		 #100;
		 A <= 'b00;
		 B <= 'b00;
		 #10;
		 B <= 'b01;
		 #10;
		 B <= 'b10;
		 #10;
		 B <= 'b11;
		 #10;
		 #100;
		 A <= 'b01;
		 B <= 'b00;
		 #10;
		 B <= 'b01;
		 #10;
		 B <= 'b10;
		 #10;
		 B <= 'b11;
		 #10;
		 #100;
		 A <= 'b10;
		 B <= 'b00;
		 #10;
		 B <= 'b01;
		 #10;
		 B <= 'b10;
		 #10;
		 B <= 'b11;
		 #10;
		 #100;
		 A <= 'b11;
		 B <= 'b00;
		 #10;
		 B <= 'b01;
		 #10;
		 B <= 'b10;
		 #10;
		 B <= 'b11;
		 #10;
		 #100;
		 
		 $finish;
	end
	initial
	begin
		$dumpfile(`DUMP_FILE_NAME);
		//$dumpfile("shift.vcd");  
		$dumpvars(1);		//writing the vcd file
	end
 	
endmodule

tests/testfiles/test_cells/shift_ab_sign/shift_ab_sign.vcd
$date
	Fri Apr 21 13:39:25 2023
$end
$version
	Icarus Verilog
$end
$timescale
	1ps
$end
$scope module tb_shift $end
$var wire 2 ! Y [1:0] $end
$var reg 2 " A [1:0] $end
$var reg 2 # B [1:0] $end
$upscope $end
$enddefinitions $end
#0
$dumpvars
bx #
bx "
bx !
$end
#100000
b0 !
b0 #
b0 "
#110000
b1 #
#120000
b10 #
#130000
b11 #
#240000
b1 !
b0 #
b1 "
#250000
b0 !
b1 #
#260000
b10 #
#270000
b10 !
b11 #
#380000
b0 #
b10 "
#390000
b1 !
b1 #
#400000
b0 !
b10 #
#410000
b11 #
#520000
b11 !
b0 #
b11 "
#530000
b1 !
b1 #
#540000
b0 !
b10 #
#550000
b10 !
b11 #
