tests/testfiles/ift/flipFlops/dlatch/dlatch_ift.v
module m_0 (D, D_t, EN, EN_t, Q, Q_t);

parameter WIDTH = 2;
parameter EN_POLARITY = 1'b1;

input EN;
input [WIDTH-1:0] D;
input [31:0] EN_t;
input [31:0] D_t;
output reg [WIDTH-1:0] Q;
output reg [31:0] Q_t;

initial begin
    Q_t = 0;
end

always @* begin
	if (EN == EN_POLARITY) begin
		Q <= D;
		Q_t <=  D_t | EN_t;
	end
end


endmodule

tests/testfiles/ift/flipFlops/dlatch/dlatch_ift_tb.v
`timescale 1ns/1ps
module dlatch_tb();
	reg [1:0] D;
	reg EN;
	wire[1:0] Q;

	reg [31:0] D_t;
	reg [31:0] EN_t;
	wire [31:0] Q_t;
	
	reg[31:0] read_data [0:1];
	integer i;
	
	m_0 d1(.D(D),.D_t(D_t), .EN(EN), .EN_t(EN_t), .Q(Q), .Q_t(Q_t));

	initial begin
  		EN=0;
     		forever #5 EN = ~EN;  
	end 

	initial begin 
		$readmemb(`INPUT_FILE_NAME, read_data);
		for(i = 0; i<=1; i+=1) begin
		{ D_t, EN_t} = read_data[i]; 
		 #10;
		 D <= 'b00;
		 #10;
		 D <= 'b01;
		 #10;
		 D <= 'b10;
		 #10;
		 D <= 'b11;
		 #10;
		 
		 end
		 $finish;
	end
	initial
	begin
		$dumpfile(`DUMP_FILE_NAME);
		//$dumpfile("../../examples/flipFlops/dlatch/dlatchExport.vcd");
		$dumpvars(1);		//writing the vcd file
	end
 	
endmodule

tests/testfiles/ift/flipFlops/dlatch/dlatch_ift.vcd
$date
	Mon Feb  5 16:42:00 2024
$end
$version
	Icarus Verilog
$end
$timescale
	1ps
$end
$scope module dlatch_tb $end
$var wire 32 ! Q_t [31:0] $end
$var wire 2 " Q [1:0] $end
$var reg 2 # D [1:0] $end
$var reg 32 $ D_t [31:0] $end
$var reg 1 % EN $end
$var reg 32 & EN_t [31:0] $end
$var integer 32 ' i [31:0] $end
$upscope $end
$enddefinitions $end
$comment Show the parameter values. $end
$dumpall
$end
#0
$dumpvars
b0 '
b0 &
0%
b0 $
bx #
bx "
b0 !
$end
#5000
1%
#10000
b0 #
0%
#15000
b0 "
1%
#20000
b1 #
0%
#25000
b1 "
1%
#30000
b10 #
0%
#35000
b10 "
1%
#40000
b11 #
0%
#45000
b11 "
1%
#50000
0%
b1 &
b1 '
#55000
b1 !
1%
#60000
b0 #
0%
#65000
b0 "
1%
#70000
b1 #
0%
#75000
b1 "
1%
#80000
b10 #
0%
#85000
b10 "
1%
#90000
b11 #
0%
#95000
b11 "
1%
#100000
0%
b10 '
