tests/testfiles/gateExample/gateExample.v
module gateExample( 
    a, b, c, d,
    e, f);
  input wire a;
  input wire b;
  input wire c;
  input wire d;
  output wire e;
  output wire f;
  wire g;
  assign g = a & b;
  assign e = g | c; 
  assign f = e & d;

endmodule

tests/testfiles/gateExample/gateExample_tb.v
module gateExample_tb;
  reg a;
  reg b;
  reg c;
  reg d;
  reg[3:0] read_data [0:15];
  integer i;
  output e;
  output f;

  gateExample d1( a, b, c, d, e, f);
  initial begin
    #0
    a=0;b=0;c=0;d=0;
    #2
    a=0;b=0;c=0;d=1;
    #2
    a=0;b=0;c=1;d=0;
    #2
    a=0;b=0;c=1;d=1;
    #2
    a=0;b=1;c=0;d=0;
    #2
    a=0;b=1;c=0;d=1;
    #2
    a=0;b=1;c=1;d=0;
    #2
    a=0;b=1;c=1;d=1;
    #2
    a=1;b=0;c=0;d=0;
    #2
    a=1;b=0;c=0;d=1;
    #2
    a=1;b=0;c=1;d=0;
    #2
    a=1;b=0;c=1;d=1;
    #2
    a=1;b=1;c=0;d=0;
    #2
    a=1;b=1;c=0;d=1;
    #2
    a=1;b=1;c=1;d=0;
    #2
    a=1;b=1;c=1;d=1;
    #2
    $finish;
  end

  initial
	begin
	    $dumpfile(`DUMP_FILE_NAME);
		//$dumpfile("gateExample.vcd");
		$dumpvars(1,  a, b, c, d, e, f);		//writing the vcd file
	end
	
	//initial
		//$monitor("At time %t, value a = %b value a = %b value a = %b", $time, a, b, c);
endmodule

tests/testfiles/gateExample/gateExample.vcd
$date
	Wed Feb 15 16:04:43 2023
$end
$version
	Icarus Verilog
$end
$timescale
	1s
$end
$scope module gateExample_tb $end
$var reg 1 ! a $end
$upscope $end
$scope module gateExample_tb $end
$var reg 1 " b $end
$upscope $end
$scope module gateExample_tb $end
$var reg 1 # c $end
$upscope $end
$scope module gateExample_tb $end
$var reg 1 $ d $end
$upscope $end
$scope module gateExample_tb $end
$var wire 1 % e $end
$upscope $end
$scope module gateExample_tb $end
$var wire 1 & f $end
$upscope $end
$enddefinitions $end
#0
$dumpvars
0&
0%
0$
0#
0"
0!
$end
#2
1$
#4
1%
0$
1#
#6
1&
1$
#8
0&
0%
0$
0#
1"
#10
1$
#12
1%
0$
1#
#14
1&
1$
#16
0&
0%
0$
0#
0"
1!
#18
1$
#20
1%
0$
1#
#22
1&
1$
#24
0&
0$
0#
1"
#26
1&
1$
#28
0&
0$
1#
#30
1&
1$
