tests/testfiles/flipFlops/dlatch/dlatch.v
module m_0 (D, EN, Q);

parameter WIDTH = 2;
parameter EN_POLARITY = 1'b1;

input EN;
input [WIDTH-1:0] D;
output reg [WIDTH-1:0] Q;

always @* begin
	if (EN == EN_POLARITY)
		Q = D;
end

endmodule

tests/testfiles/flipFlops/dlatch/dlatch_tb.v
`timescale 1ns/1ps
module tb_DLATCH();
	reg [1:0] D;
	reg EN;
	wire[1:0] Q;

	m_0 d1(.D(D), .EN(EN), .Q(Q));

	initial begin
  		EN=0;
     		forever #10 EN = ~EN;  
	end 

	initial begin 
		 #100;
		 D <= 'b00;
		 #100;
		 D <= 'b01;
		 #100;
		 D <= 'b10;
		 #100;
		 D <= 'b11;
		 #100;
		 
		 $finish;
	end
	initial
	begin
		$dumpfile(`DUMP_FILE_NAME);
		//$dumpfile("../../examples/flipFlops/dlatch/dlatchExport.vcd");
		$dumpvars(0,EN,D,Q);		//writing the vcd file
	end
 	
endmodule

tests/testfiles/flipFlops/dlatch/dlatch.vcd
$date
	Mon Feb 20 11:26:34 2023
$end
$version
	Icarus Verilog
$end
$timescale
	1ps
$end
$scope module tb_DLATCH $end
$var reg 1 ! EN $end
$upscope $end
$scope module tb_DLATCH $end
$var reg 2 " D [1:0] $end
$upscope $end
$scope module tb_DLATCH $end
$var wire 2 # Q [1:0] $end
$upscope $end
$enddefinitions $end
#0
$dumpvars
bx #
bx "
0!
$end
#10000
1!
#20000
0!
#30000
1!
#40000
0!
#50000
1!
#60000
0!
#70000
1!
#80000
0!
#90000
1!
#100000
b0 "
0!
#110000
b0 #
1!
#120000
0!
#130000
1!
#140000
0!
#150000
1!
#160000
0!
#170000
1!
#180000
0!
#190000
1!
#200000
b1 "
0!
#210000
b1 #
1!
#220000
0!
#230000
1!
#240000
0!
#250000
1!
#260000
0!
#270000
1!
#280000
0!
#290000
1!
#300000
b10 "
0!
#310000
b10 #
1!
#320000
0!
#330000
1!
#340000
0!
#350000
1!
#360000
0!
#370000
1!
#380000
0!
#390000
1!
#400000
b11 "
0!
#410000
b11 #
1!
#420000
0!
#430000
1!
#440000
0!
#450000
1!
#460000
0!
#470000
1!
#480000
0!
#490000
1!
#500000
0!
