tests/testfiles/flipFlops/dffsr/dffsr.v
/* Generated by Yosys 0.20 (git sha1 4fcb95ed087, clang  -fPIC -Os) */

(* src = "dffsr.v:1.1-29.10" *)
module m_0(CLK, SET, CLR, D, Q);
  (* src = "dffsr.v:8.7-8.10" *)
  input CLK;
  wire CLK;
  (* src = "dffsr.v:9.24-9.27" *)
  input CLR;
  wire CLR;
  (* src = "dffsr.v:9.29-9.30" *)
  input D;
  wire D;
  (* src = "dffsr.v:10.24-10.25" *)
  output Q;
  reg Q;
  (* src = "dffsr.v:9.19-9.22" *)
  input SET;
  wire SET;
  (* src = "dffsr.v:19.3-25.18" *)
  always @(posedge CLK, posedge SET, posedge CLR)
    if (CLR) Q <= 1'b0;
    else if (SET) Q <= 1'b1;
    else Q <= D;
endmodule

tests/testfiles/flipFlops/dffsr/dffsr_tb.v
`timescale 1us/100ns
module tb_DFFSR();
	reg D;
	reg SET;
	reg CLR;
	reg clk;
	wire Q;
	
	m_0 d1(.CLK(clk), .SET(SET), .CLR(CLR), .D(D), .Q(Q));

	initial begin
  		clk=0;
     		forever #10 clk = ~clk;  
	end 

	initial begin 
		 #40;
		 D <= 'b0;
		 SET <= 'b0;
		 CLR <= 'b0;
		 #5;
		 CLR <= 'b0;
		 #5;
		 CLR <= 'b1;
		 #40;
		 D <= 'b0;
		 SET <= 'b0;
		 #5;
		 CLR <= 'b1;
		 #5;
		 CLR <= 'b0;
		 #40;
		 D <= 'b0;
		 SET <= 'b1;
		 #5;
		 CLR <= 'b1;
		 #5;
		 CLR <= 'b10;
		 #40;
		 D <= 'b1;
		 SET <= 'b0;
		 #5;
		 CLR <= 'b0;
		 #5;
		 CLR <= 'b1;
		 #40;
		 D <= 'b0;
		 SET <= 'b1;
		 CLR <= 'b0;
		 #5;
		 CLR <= 'b0;
		 #5;
		 CLR <= 'b1;
		 #40;
		 D <= 'b0;
		 SET <= 'b0;
		 #5;
		 CLR <= 'b1;
		 #5;
		 CLR <= 'b1;
		 #40;
		 D <= 'b1;
		 SET <= 'b0;
		 #5;
		 CLR <= 'b1;
		 #5;
		 CLR <= 'b0;
		 #40;
		 D <= 'b1;
		 SET <= 'b0;
		 #5;
		 CLR <= 'b1;
		 #5;
		 CLR <= 'b0;
		 #40;
		 D <= 'b0;
		 SET <= 'b1;
		 CLR <= 'b0;
		 #5;
		 CLR <= 'b1;
		 #5;
		 CLR <= 'b1;
		 #40;
		 D <= 'b0;
		 SET <= 'b1;
		 #5;
		 CLR <= 'b0;
		 #5;
		 CLR <= 'b1;
		 #40;
		 D <= 'b1;
		 SET <= 'b1;
		 #5;
		 CLR <= 'b0;
		 #5;
		 CLR <= 'b1;
		 #40;
	
		 $finish;
	end
	initial
	begin
		$dumpfile(`DUMP_FILE_NAME);
		//$dumpfile("dffsr.vcd");
		$dumpvars(1);		//writing the vcd file
	end
 	
endmodule

tests/testfiles/flipFlops/dffsr/dffsr.vcd
$date
	Thu Apr 20 17:48:33 2023
$end
$version
	Icarus Verilog
$end
$timescale
	100ns
$end
$scope module tb_DFFSR $end
$var wire 1 ! Q $end
$var reg 1 " CLR $end
$var reg 1 # D $end
$var reg 1 $ SET $end
$var reg 1 % clk $end
$upscope $end
$enddefinitions $end
#0
$dumpvars
0%
x$
x#
x"
x!
$end
#100
1%
#200
0%
#300
1%
#400
0"
0$
0#
0%
#500
0!
1"
1%
#600
0%
#700
1%
#800
0%
#900
1%
#1000
0"
0%
#1100
1%
#1200
0%
#1300
1%
#1400
1!
1$
0%
#1450
0!
1"
#1500
0"
1%
#1600
0%
#1700
1!
1%
#1800
0%
#1900
0$
1#
1%
#2000
0!
1"
0%
#2100
1%
#2200
0%
#2300
1%
#2400
1!
0"
1$
0#
0%
#2500
0!
1"
1%
#2600
0%
#2700
1%
#2800
0%
#2900
0$
1%
#3000
0%
#3100
1%
#3200
0%
#3300
1%
#3400
1#
0%
#3500
0"
1%
#3600
0%
#3700
1!
1%
#3800
0%
#3900
1%
#3950
0!
1"
#4000
0"
0%
#4100
1!
1%
#4200
0%
#4300
1%
#4400
1$
0#
0%
#4450
0!
1"
#4500
1%
#4600
0%
#4700
1%
#4800
0%
#4900
1%
#4950
0"
#5000
1"
0%
#5100
1%
#5200
0%
#5300
1%
#5400
1#
0%
#5450
0"
#5500
0!
1"
1%
