tests/testfiles/ift_flow/design/design.v
module M(a,b,c);
 input a,b;
 output c;

 assign c = a & b;  

endmodule

module des(a, b, s, c);
 input a,b,s;
 wire d;
 output c;

 M m1(a,b,d);

 assign c = s ? d : !b;
endmodule

tests/testfiles/ift_flow/design/design_tb.v
module design_tb;
   reg a,b,s;
   wire c;
// values for hierarchy ift flow test
  initial begin
      a = 0;
      b = 0;
      s = 0;
      #1;
      a = 0;
      b = 1;
      s = 0;
      #1;
      a = 1;
      b = 0;
      s = 0;
      #1;
      a = 1;
      b = 1;
      s = 0;
      #1;
      a = 0;
      b = 0;
      s = 1;
      #1;
      a = 0;
      b = 1;
      s = 1;
      #1;
      a = 1;
      b = 0;
      s = 1;
      #1;
      a = 1;
      b = 1;
      s = 1;
   end

   des t1(.a(a), .s(s), .b(b), .c(c));
  
   initial
      begin
         $dumpfile(`DUMP_FILE_NAME);
        $dumpvars(1);		//writing the vcd file
      end
      
   //initial
      //$monitor("At time %t, value = %h (%0d)", $time, a, b, c);

endmodule

tests/testfiles/ift_flow/design/design.vcd
$date
	Fri May 26 14:01:26 2023
$end
$version
	Icarus Verilog
$end
$timescale
	1s
$end
$scope module design_tb $end
$var wire 1 ! c $end
$var reg 1 " a $end
$var reg 1 # b $end
$var reg 1 $ s $end
$upscope $end
$enddefinitions $end
#0
$dumpvars
0$
0#
0"
1!
$end
#8
0!
1#
#16
1!
0#
1"
#24
0!
1#
#32
1$
0#
0"
#40
1#
#48
0#
1"
#56
1!
1#
