tests/testfiles/flipFlops/adff/adff.v
module m_0(ARST, CLK, D, Q);

parameter WIDTH = 2;
parameter CLK_POLARITY = 1'b1;
parameter ARST_POLARITY = 1'b1;
parameter ARST_VALUE = 2;

input CLK, ARST;
input [WIDTH-1:0] D;
output reg [WIDTH-1:0] Q;
wire pos_clk = CLK == CLK_POLARITY;
wire pos_arst = ARST == ARST_POLARITY;

always @(posedge pos_clk, posedge pos_arst) begin
	if (pos_arst)
		Q <= ARST_VALUE;
	else
		Q <= D;
end

endmodule

tests/testfiles/flipFlops/adff/adff_tb_gf.v
`timescale 1ns/1ps
module tb_ADFF();
  parameter WIDTH= 5;
	reg [WIDTH-1:0] D;
	reg clk;
	wire[WIDTH-1:0] Q;
	reg ARST;

	m_0 #(WIDTH) d1(.ARST(ARST),.CLK(clk),.D(D),.Q(Q));

	initial begin
  		clk=0;
     		forever #10 clk = ~clk;  
	end 
	initial begin
  		D=0;
      forever #1 D= D+1;  
	end 


	initial begin 
		 #40;
		 D <= 'b00;
		 #5;
		 ARST <= 1;
		 #5;
		 ARST <= 0;
		 #40;
		 D <= 'b01;
		 #5;
		 ARST <= 1;
		 #5;
		 ARST <= 0;
		 #40;
		 D <= 'b10;
		 #5;
		 ARST <= 1;
		 #5;
		 ARST <= 0;
		 #40;
		 D <= 'b11;
		 #5;
		 ARST <= 1;
		 #5;
		 ARST <= 0;
		 #40;
		 
		 $finish;
	end
	initial
	begin
		$dumpfile("adff_gf.vcd");
		$dumpvars(0,ARST,clk,D,Q);		//writing the vcd file
	end
 	
endmodule

tests/testfiles/flipFlops/adff/adff.vcd
$date
	Mon Feb 20 11:26:34 2023
$end
$version
	Icarus Verilog
$end
$timescale
	1ps
$end
$scope module tb_ADFF $end
$var reg 1 ! ARST $end
$upscope $end
$scope module tb_ADFF $end
$var reg 1 " clk $end
$upscope $end
$scope module tb_ADFF $end
$var reg 2 # D [1:0] $end
$upscope $end
$scope module tb_ADFF $end
$var wire 2 $ Q [1:0] $end
$upscope $end
$enddefinitions $end
#0
$dumpvars
bx $
bx #
0"
x!
$end
#10000
1"
#20000
0"
#30000
1"
#40000
b0 #
0"
#45000
b10 $
1!
#50000
0!
1"
#60000
0"
#70000
b0 $
1"
#80000
0"
#90000
b1 #
1"
#95000
b10 $
1!
#100000
0!
0"
#110000
b1 $
1"
#120000
0"
#130000
1"
#140000
b10 #
0"
#145000
b10 $
1!
#150000
0!
1"
#160000
0"
#170000
1"
#180000
0"
#190000
b11 #
1"
#195000
1!
#200000
0!
0"
#210000
b11 $
1"
