tests/testfiles/ift/flipFlops/dlatchsr_1bit/dlatchsr_1bit_ift.v
/* Generated by Yosys 0.20 (git sha1 4fcb95ed087, clang  -fPIC -Os) */

(* dynports =  1  *)
(* src = "dlatch.v:1.1-15.10" *)
module m_0(CLR, CLR_t, D, D_t, EN, EN_t, Q, Q_t, SET, SET_t);
  (* src = "dlatch.v:7.19-7.20" *)
  input CLR;
  wire CLR;
  (* src = "dlatch.v:7.19-7.20" *)
  input D;
  wire D;
  (* src = "dlatch.v:6.7-6.9" *)
  input EN;
  wire EN;
  (* src = "dlatch.v:8.24-8.25" *)
  output Q;
  reg Q;
  (* src = "dlatch.v:7.19-7.20" *)
  input SET;
  wire SET;
   input [31:0] EN_t;
  input [31:0] D_t;
  input [31:0] SET_t;
  input [31:0] CLR_t;
  output reg [31:0] Q_t;
  (* src = "dlatch.v:10.1-13.4" *)

  initial begin
      Q_t = 0;
  end

  always @*
    if (CLR)begin
     Q <= 1'b0;
     Q_t <= CLR_t;
     end
    else if (SET) begin
     Q <= 1'b1;
     Q_t <= SET_t;
     end
    else if (EN)begin
     Q = D;
     Q_t = D_t | EN_t;
     end
endmodule

tests/testfiles/ift/flipFlops/dlatchsr_1bit/dlatchsr_1bit_ift_tb.v
`timescale 1us/100ns
module dlatchsr_1bit_tb();
	reg  D;
	reg SET;
	reg  CLR;
	reg EN;
	wire Q;
	
	reg [31:0] D_t;
	reg [31:0] EN_t;
	reg [31:0] CLR_t;
	reg [31:0] SET_t;
	wire [31:0] Q_t;
	
	
	reg[127:0] read_data [0:15];
	integer i;
	
	m_0 d1(.CLR(CLR),.CLR_t(CLR_t), .D(D), .D_t(D_t), .EN(EN),.EN_t(EN_t), .Q(Q), .Q_t(Q_t),.SET(SET), .SET_t(SET_t));

	initial begin
  		EN=0;
     		forever #10 EN = ~EN;  
	end 

	initial begin 
	$readmemb(`INPUT_FILE_NAME, read_data);
		for(i = 0; i<=15; i+=1) begin
		{ D_t, EN_t, CLR_t, SET_t} = read_data[i]; 
		 #40;
		 D <= 'b0;
		 SET <= 'b0;
		 CLR <= 'b0;
		 #5;
		 CLR <= 'b1;
		 #40;
		 D <= 'b1;
		 SET <= 'b0;
		 #5;
		 CLR <= 'b0;
		 #5;
		 CLR <= 'b1;
		 #40;
		 D <= 'b0;
		 SET <= 'b1;
		 CLR <= 'b0;
		 #5;
		 CLR <= 'b1;
		 #40;
		 D <= 'b1;
		 SET <= 'b1;
		 #5;
		 CLR <= 'b0;
		 #5;
		 CLR <= 'b1;
		 #40;
		 end
		 $finish;
	end
	initial
	begin
		$dumpfile(`DUMP_FILE_NAME);
		//$dumpfile("dlatchsr.vcd");
		$dumpvars(1);		//writing the vcd file
	end
 	
endmodule

tests/testfiles/ift/flipFlops/dlatchsr_1bit/dlatchsr_1bit_ift.vcd
$date
	Mon Feb  5 16:42:00 2024
$end
$version
	Icarus Verilog
$end
$timescale
	100ns
$end
$scope module dlatchsr_1bit_tb $end
$var wire 32 ! Q_t [31:0] $end
$var wire 1 " Q $end
$var reg 1 # CLR $end
$var reg 32 $ CLR_t [31:0] $end
$var reg 1 % D $end
$var reg 32 & D_t [31:0] $end
$var reg 1 ' EN $end
$var reg 32 ( EN_t [31:0] $end
$var reg 1 ) SET $end
$var reg 32 * SET_t [31:0] $end
$var integer 32 + i [31:0] $end
$upscope $end
$enddefinitions $end
$comment Show the parameter values. $end
$dumpall
$end
#0
$dumpvars
b0 +
b0 *
x)
b0 (
0'
b0 &
x%
b0 $
x#
x"
b0 !
$end
#100
1'
#200
0'
#300
1'
#400
0#
0)
0%
0'
#450
0"
1#
#500
1'
#600
0'
#700
1'
#800
0'
#850
1%
#900
1"
0#
1'
#950
0"
1#
#1000
0'
#1100
1'
#1200
0'
#1300
1'
#1350
1"
0#
1)
0%
#1400
0"
1#
0'
#1500
1'
#1600
0'
#1700
1'
#1800
1%
0'
#1850
1"
0#
#1900
0"
1#
1'
#2000
0'
#2100
1'
#2200
0'
#2300
1'
b1000 *
b1 +
#2400
0'
#2500
1'
#2600
0'
#2700
0#
0)
0%
1'
#2750
1#
#2800
0'
#2900
1'
#3000
0'
#3100
1'
#3150
1%
#3200
0#
0'
#3250
1#
#3300
1'
#3400
0'
#3500
1'
#3600
0'
#3650
b1000 !
1"
0#
1)
0%
#3700
b0 !
0"
1#
1'
#3800
0'
#3900
1'
#4000
0'
#4100
1%
1'
#4150
b1000 !
1"
0#
#4200
b0 !
0"
1#
0'
#4300
1'
#4400
0'
#4500
1'
#4600
b100 !
0'
b100 $
b0 *
b10 +
#4700
1'
#4800
0'
#4900
1'
#5000
0#
0)
0%
0'
#5050
1#
#5100
1'
#5200
0'
#5300
1'
#5400
0'
#5450
1%
#5500
b0 !
1"
0#
1'
#5550
b100 !
0"
1#
#5600
0'
#5700
1'
#5800
0'
#5900
1'
#5950
b0 !
1"
0#
1)
0%
#6000
b100 !
0"
1#
0'
#6100
1'
#6200
0'
#6300
1'
#6400
1%
0'
#6450
b0 !
1"
0#
#6500
b100 !
0"
1#
1'
#6600
0'
#6700
1'
#6800
0'
#6900
1'
b1000 *
b11 +
#7000
0'
#7100
1'
#7200
0'
#7300
b0 !
0#
0)
0%
1'
#7350
b100 !
1#
#7400
0'
#7500
1'
#7600
0'
#7700
1'
#7750
1%
#7800
0#
0'
#7850
1#
#7900
1'
#8000
0'
#8100
1'
#8200
0'
#8250
b1000 !
1"
0#
1)
0%
#8300
b100 !
0"
1#
1'
#8400
0'
#8500
1'
#8600
0'
#8700
1%
1'
#8750
b1000 !
1"
0#
#8800
b100 !
0"
1#
0'
#8900
1'
#9000
0'
#9100
1'
#9200
b0 !
0'
b10 (
b0 $
b0 *
b100 +
#9300
1'
#9400
0'
#9500
1'
#9600
0#
0)
0%
0'
#9650
1#
#9700
1'
#9800
0'
#9900
1'
#10000
0'
#10050
1%
#10100
b10 !
1"
0#
1'
#10150
b0 !
0"
1#
#10200
0'
#10300
1'
#10400
0'
#10500
1'
#10550
1"
0#
1)
0%
#10600
0"
1#
0'
#10700
1'
#10800
0'
#10900
1'
#11000
1%
0'
#11050
1"
0#
#11100
0"
1#
1'
#11200
0'
#11300
1'
#11400
0'
#11500
1'
b1000 *
b101 +
#11600
0'
#11700
1'
#11800
0'
#11900
b10 !
0#
0)
0%
1'
#11950
b0 !
1#
#12000
0'
#12100
1'
#12200
0'
#12300
1'
#12350
1%
#12400
0#
0'
#12450
1#
#12500
1'
#12600
0'
#12700
1'
#12800
0'
#12850
b1000 !
1"
0#
1)
0%
#12900
b0 !
0"
1#
1'
#13000
0'
#13100
1'
#13200
0'
#13300
1%
1'
#13350
b1000 !
1"
0#
#13400
b0 !
0"
1#
0'
#13500
1'
#13600
0'
#13700
1'
#13800
b100 !
0'
b100 $
b0 *
b110 +
#13900
1'
#14000
0'
#14100
1'
#14200
0#
0)
0%
0'
#14250
1#
#14300
1'
#14400
0'
#14500
1'
#14600
0'
#14650
1%
#14700
b10 !
1"
0#
1'
#14750
b100 !
0"
1#
#14800
0'
#14900
1'
#15000
0'
#15100
1'
#15150
b0 !
1"
0#
1)
0%
#15200
b100 !
0"
1#
0'
#15300
1'
#15400
0'
#15500
1'
#15600
1%
0'
#15650
b0 !
1"
0#
#15700
b100 !
0"
1#
1'
#15800
0'
#15900
1'
#16000
0'
#16100
1'
b1000 *
b111 +
#16200
0'
#16300
1'
#16400
0'
#16500
b10 !
0#
0)
0%
1'
#16550
b100 !
1#
#16600
0'
#16700
1'
#16800
0'
#16900
1'
#16950
1%
#17000
0#
0'
#17050
1#
#17100
1'
#17200
0'
#17300
1'
#17400
0'
#17450
b1000 !
1"
0#
1)
0%
#17500
b100 !
0"
1#
1'
#17600
0'
#17700
1'
#17800
0'
#17900
1%
1'
#17950
b1000 !
1"
0#
#18000
b100 !
0"
1#
0'
#18100
1'
#18200
0'
#18300
1'
#18400
b0 !
0'
b1 &
b0 (
b0 $
b0 *
b1000 +
#18500
1'
#18600
0'
#18700
1'
#18800
0#
0)
0%
0'
#18850
1#
#18900
1'
#19000
0'
#19100
1'
#19200
0'
#19250
1%
#19300
b1 !
1"
0#
1'
#19350
b0 !
0"
1#
#19400
0'
#19500
1'
#19600
0'
#19700
1'
#19750
1"
0#
1)
0%
#19800
0"
1#
0'
#19900
1'
#20000
0'
#20100
1'
#20200
1%
0'
#20250
1"
0#
#20300
0"
1#
1'
#20400
0'
#20500
1'
#20600
0'
#20700
1'
b1000 *
b1001 +
#20800
0'
#20900
1'
#21000
0'
#21100
b1 !
0#
0)
0%
1'
#21150
b0 !
1#
#21200
0'
#21300
1'
#21400
0'
#21500
1'
#21550
1%
#21600
0#
0'
#21650
1#
#21700
1'
#21800
0'
#21900
1'
#22000
0'
#22050
b1000 !
1"
0#
1)
0%
#22100
b0 !
0"
1#
1'
#22200
0'
#22300
1'
#22400
0'
#22500
1%
1'
#22550
b1000 !
1"
0#
#22600
b0 !
0"
1#
0'
#22700
1'
#22800
0'
#22900
1'
#23000
b100 !
0'
b100 $
b0 *
b1010 +
#23100
1'
#23200
0'
#23300
1'
#23400
0#
0)
0%
0'
#23450
1#
#23500
1'
#23600
0'
#23700
1'
#23800
0'
#23850
1%
#23900
b1 !
1"
0#
1'
#23950
b100 !
0"
1#
#24000
0'
#24100
1'
#24200
0'
#24300
1'
#24350
b0 !
1"
0#
1)
0%
#24400
b100 !
0"
1#
0'
#24500
1'
#24600
0'
#24700
1'
#24800
1%
0'
#24850
b0 !
1"
0#
#24900
b100 !
0"
1#
1'
#25000
0'
#25100
1'
#25200
0'
#25300
1'
b1000 *
b1011 +
#25400
0'
#25500
1'
#25600
0'
#25700
b1 !
0#
0)
0%
1'
#25750
b100 !
1#
#25800
0'
#25900
1'
#26000
0'
#26100
1'
#26150
1%
#26200
0#
0'
#26250
1#
#26300
1'
#26400
0'
#26500
1'
#26600
0'
#26650
b1000 !
1"
0#
1)
0%
#26700
b100 !
0"
1#
1'
#26800
0'
#26900
1'
#27000
0'
#27100
1%
1'
#27150
b1000 !
1"
0#
#27200
b100 !
0"
1#
0'
#27300
1'
#27400
0'
#27500
1'
#27600
b0 !
0'
b10 (
b0 $
b0 *
b1100 +
#27700
1'
#27800
0'
#27900
1'
#28000
0#
0)
0%
0'
#28050
1#
#28100
1'
#28200
0'
#28300
1'
#28400
0'
#28450
1%
#28500
b11 !
1"
0#
1'
#28550
b0 !
0"
1#
#28600
0'
#28700
1'
#28800
0'
#28900
1'
#28950
1"
0#
1)
0%
#29000
0"
1#
0'
#29100
1'
#29200
0'
#29300
1'
#29400
1%
0'
#29450
1"
0#
#29500
0"
1#
1'
#29600
0'
#29700
1'
#29800
0'
#29900
1'
b1000 *
b1101 +
#30000
0'
#30100
1'
#30200
0'
#30300
b11 !
0#
0)
0%
1'
#30350
b0 !
1#
#30400
0'
#30500
1'
#30600
0'
#30700
1'
#30750
1%
#30800
0#
0'
#30850
1#
#30900
1'
#31000
0'
#31100
1'
#31200
0'
#31250
b1000 !
1"
0#
1)
0%
#31300
b0 !
0"
1#
1'
#31400
0'
#31500
1'
#31600
0'
#31700
1%
1'
#31750
b1000 !
1"
0#
#31800
b0 !
0"
1#
0'
#31900
1'
#32000
0'
#32100
1'
#32200
b100 !
0'
b100 $
b0 *
b1110 +
#32300
1'
#32400
0'
#32500
1'
#32600
0#
0)
0%
0'
#32650
1#
#32700
1'
#32800
0'
#32900
1'
#33000
0'
#33050
1%
#33100
b11 !
1"
0#
1'
#33150
b100 !
0"
1#
#33200
0'
#33300
1'
#33400
0'
#33500
1'
#33550
b0 !
1"
0#
1)
0%
#33600
b100 !
0"
1#
0'
#33700
1'
#33800
0'
#33900
1'
#34000
1%
0'
#34050
b0 !
1"
0#
#34100
b100 !
0"
1#
1'
#34200
0'
#34300
1'
#34400
0'
#34500
1'
b1000 *
b1111 +
#34600
0'
#34700
1'
#34800
0'
#34900
b11 !
0#
0)
0%
1'
#34950
b100 !
1#
#35000
0'
#35100
1'
#35200
0'
#35300
1'
#35350
1%
#35400
0#
0'
#35450
1#
#35500
1'
#35600
0'
#35700
1'
#35800
0'
#35850
b1000 !
1"
0#
1)
0%
#35900
b100 !
0"
1#
1'
#36000
0'
#36100
1'
#36200
0'
#36300
1%
1'
#36350
b1000 !
1"
0#
#36400
b100 !
0"
1#
0'
#36500
1'
#36600
0'
#36700
1'
#36800
0'
b10000 +
