tests/testfiles/ift/flipFlops/mbit_dffsre/mbit_dffsre_ift.v
/* Generated by Yosys 0.20 (git sha1 4fcb95ed087, clang  -fPIC -Os) */

(* dynports =  1  *)
(* src = "dlatch.v:1.1-15.10" *)
module m_0(CLR, CLR_t, D, D_t, CLK, CLK_t,EN, EN_t, Q, Q_t, SET, SET_t);
  (* src = "dlatch.v:6.7-6.9" *)
  input CLK;
  wire CLK;
  (* src = "dlatch.v:7.19-7.20" *)
  input [1:0] CLR;
  wire [1:0] CLR;
  (* src = "dlatch.v:7.19-7.20" *)
  input [1:0] D;
  wire [1:0] D;
  (* src = "dlatch.v:7.19-7.20" *)
  input EN;
  wire EN;
  (* src = "dlatch.v:8.24-8.25" *)
  output [1:0] Q;
  reg [1:0] Q;
  (* src = "dlatch.v:7.19-7.20" *)
  input [1:0] SET;
  wire [1:0] SET;
  
   input [31:0] CLK_t;
  input [31:0] D_t;
  input [31:0] SET_t;
  input [31:0] CLR_t;
  input [31:0] EN_t;
  output reg [31:0] Q_t = 0;
  (* src = "dlatch.v:10.1-13.4" *)
  always @(posedge CLK, posedge SET[0], posedge CLR[0])begin
    if (CLR[0]) begin
    Q[0] <= 1'b0;
    Q_t <= CLR_t;
    end
    else if (SET[0])begin
     Q[0] <= 1'b1;
     Q_t <= SET_t;
     end
    else if(EN) begin
    Q[0] <= D[0];
    Q_t <= D_t | EN_t;
    end
    end
  (* src = "dlatch.v:10.1-13.4" *)
   always @(posedge CLK, posedge SET[1], posedge CLR[1])begin
    if (CLR[1]) begin
    Q[1] <= 1'b0;
    Q_t <= CLR_t;
    end
    else if (SET[1])begin
     Q[1] <= 1'b1;
     Q_t <= SET_t;
     end
    else if(EN)begin
    Q[1] <= D[1];
    Q_t <= D_t | EN_t;
    end
    end
endmodule

tests/testfiles/ift/flipFlops/mbit_dffsre/mbit_dffsre_ift_tb.v
`timescale 1us/100ns
module mbit_dffsre_tb();
	reg [1:0] D;
	reg [1:0] SET;
	reg [1:0] CLR;
	reg clk;
	reg EN;
	wire[1:0] Q;
	
	reg [31:0] D_t;
	reg [31:0] EN_t;
	reg [31:0] CLK_t = 0;
	reg [31:0] CLR_t;
	reg [31:0] SET_t;
	wire [31:0] Q_t;
	
	reg[127:0] read_data [0:15];
	integer i;
	

	m_0 d1(.CLR(CLR),.CLR_t(CLR_t), .D(D), .D_t(D_t), .CLK(clk),.CLK_t(CLK_t), .Q(Q), .Q_t(Q_t),.SET(SET), .SET_t(SET_t), .EN(EN),.EN_t(EN_t));

	initial begin
  		clk=0;
     		forever #10 clk = ~clk;  
	end 

	initial begin 
	$readmemb(`INPUT_FILE_NAME, read_data);
		for(i = 0; i<=15; i+=1) begin
		{ D_t, CLR_t, SET_t, EN_t} = read_data[i]; 
		 #40;
		 EN <= 1;
		 D <= 'b00;
		 SET <= 'b00;
		 CLR <= 'b00;
		 #5;
		 CLR <= 'b10;
		 #5;
		 CLR <= 'b11;
		 #40;
		 D <= 'b01;
		 SET <= 'b00;
		 #5;
		 CLR <= 'b10;
		 #5;
		 CLR <= 'b11;
		 #40;
		 D <= 'b10;
		 SET <= 'b00;
		 #5;
		 CLR <= 'b10;
		 #5;
		 CLR <= 'b11;
		 #40;
		 D <= 'b11;
		 SET <= 'b00;
		 #5;
		 CLR <= 'b10;
		 #5;
		 CLR <= 'b11;
		 #40;
		 D <= 'b00;
		 SET <= 'b01;
		 CLR <= 'b00;
		 #5;
		 CLR <= 'b10;
		 #5;
		 CLR <= 'b11;
		 #40;
		 D <= 'b01;
		 SET <= 'b01;
		 #5;
		 CLR <= 'b10;
		 #5;
		 CLR <= 'b11;
		 #40;
		 D <= 'b10;
		 SET <= 'b01;
		 #5;
		 CLR <= 'b10;
		 #5;
		 CLR <= 'b11;
		 #40;
		 D <= 'b11;
		 SET <= 'b01;
		 #5;
		 CLR <= 'b10;
		 #5;
		 CLR <= 'b11;
		 #40;
		 D <= 'b00;
		 SET <= 'b11;
		 CLR <= 'b00;
		 #5;
		 CLR <= 'b10;
		 #5;
		 CLR <= 'b11;
		 #40;
		 D <= 'b01;
		 SET <= 'b11;
		 #5;
		 CLR <= 'b10;
		 #5;
		 CLR <= 'b11;
		 #40;
		 D <= 'b10;
		 SET <= 'b11;
		 #5;
		 CLR <= 'b10;
		 #5;
		 CLR <= 'b11;
		 #40;
		 D <= 'b11;
		 SET <= 'b11;
		 #5;
		 CLR <= 'b10;
		 #5;
		 CLR <= 'b11;
		 #40;
		 D <= 'b00;
		 SET <= 'b10;
		 CLR <= 'b00;
		 #5;
		 CLR <= 'b10;
		 #5;
		 CLR <= 'b11;
		 #40;
		 D <= 'b01;
		 SET <= 'b10;
		 #5;
		 CLR <= 'b10;
		 #5;
		 CLR <= 'b11;
		 #40;
		 D <= 'b10;
		 SET <= 'b10;
		 #5;
		 CLR <= 'b10;
		 #5;
		 CLR <= 'b11;
		 #40;
		 D <= 'b11;
		 SET <= 'b10;
		 #5;
		 CLR <= 'b10;
		 #5;
		 CLR <= 'b11;
		 #40;
		 EN <= 0;
		 D <= 'b00;
		 SET <= 'b00;
		 CLR <= 'b00;
		 #5;
		 CLR <= 'b10;
		 #5;
		 CLR <= 'b11;
		 #40;
		 D <= 'b01;
		 SET <= 'b00;
		 #5;
		 CLR <= 'b10;
		 #5;
		 CLR <= 'b11;
		 #40;
		 D <= 'b10;
		 SET <= 'b00;
		 #5;
		 CLR <= 'b10;
		 #5;
		 CLR <= 'b11;
		 #40;
		 D <= 'b11;
		 SET <= 'b00;
		 #5;
		 CLR <= 'b10;
		 #5;
		 CLR <= 'b11;
		 #40;
		 D <= 'b00;
		 SET <= 'b01;
		 CLR <= 'b00;
		 #5;
		 CLR <= 'b10;
		 #5;
		 CLR <= 'b11;
		 #40;
		 D <= 'b01;
		 SET <= 'b01;
		 #5;
		 CLR <= 'b10;
		 #5;
		 CLR <= 'b11;
		 #40;
		 D <= 'b10;
		 SET <= 'b01;
		 #5;
		 CLR <= 'b10;
		 #5;
		 CLR <= 'b11;
		 #40;
		 D <= 'b11;
		 SET <= 'b01;
		 #5;
		 CLR <= 'b10;
		 #5;
		 CLR <= 'b11;
		 #40;
		 D <= 'b00;
		 SET <= 'b11;
		 CLR <= 'b00;
		 #5;
		 CLR <= 'b10;
		 #5;
		 CLR <= 'b11;
		 #40;
		 D <= 'b01;
		 SET <= 'b11;
		 #5;
		 CLR <= 'b10;
		 #5;
		 CLR <= 'b11;
		 #40;
		 D <= 'b10;
		 SET <= 'b11;
		 #5;
		 CLR <= 'b10;
		 #5;
		 CLR <= 'b11;
		 #40;
		 D <= 'b11;
		 SET <= 'b11;
		 #5;
		 CLR <= 'b10;
		 #5;
		 CLR <= 'b11;
		 #40;
		 D <= 'b00;
		 SET <= 'b10;
		 CLR <= 'b00;
		 #5;
		 CLR <= 'b10;
		 #5;
		 CLR <= 'b11;
		 #40;
		 D <= 'b01;
		 SET <= 'b10;
		 #5;
		 CLR <= 'b10;
		 #5;
		 CLR <= 'b11;
		 #40;
		 D <= 'b10;
		 SET <= 'b10;
		 #5;
		 CLR <= 'b10;
		 #5;
		 CLR <= 'b11;
		 #40;
		 D <= 'b11;
		 SET <= 'b10;
		 #5;
		 CLR <= 'b10;
		 #5;
		 CLR <= 'b11;
		 #40;
		 end
		 
		 $finish;
	end
	initial
	begin
		$dumpfile(`DUMP_FILE_NAME);
		//$dumpfile("2BitDffsre.vcd");
		$dumpvars(1);		//writing the vcd file
	end
 	
endmodule

tests/testfiles/ift/flipFlops/mbit_dffsre/mbit_dffsre_ift.vcd
$date
	Mon Feb  5 16:42:00 2024
$end
$version
	Icarus Verilog
$end
$timescale
	100ns
$end
$scope module mbit_dffsre_tb $end
$var wire 32 ! Q_t [31:0] $end
$var wire 2 " Q [1:0] $end
$var reg 32 # CLK_t [31:0] $end
$var reg 2 $ CLR [1:0] $end
$var reg 32 % CLR_t [31:0] $end
$var reg 2 & D [1:0] $end
$var reg 32 ' D_t [31:0] $end
$var reg 1 ( EN $end
$var reg 32 ) EN_t [31:0] $end
$var reg 2 * SET [1:0] $end
$var reg 32 + SET_t [31:0] $end
$var reg 1 , clk $end
$var integer 32 - i [31:0] $end
$upscope $end
$enddefinitions $end
$comment Show the parameter values. $end
$dumpall
$end
#0
$dumpvars
b0 -
0,
b0 +
bx *
b0 )
x(
b0 '
bx &
b0 %
bx $
b0 #
bx "
b0 !
$end
#100
1,
#200
0,
#300
1,
#400
b0 $
b0 *
b0 &
1(
0,
#450
b0x "
b10 $
#500
b0 "
b11 $
1,
#600
0,
#700
1,
#800
0,
#900
b1 &
1,
#950
b10 $
#1000
b11 $
0,
#1100
1,
#1200
0,
#1300
1,
#1400
b10 &
0,
#1450
b10 $
#1500
b11 $
1,
#1600
0,
#1700
1,
#1800
0,
#1900
b11 &
1,
#1950
b10 $
#2000
b11 $
0,
#2100
1,
#2200
0,
#2300
1,
#2400
b1 "
b0 $
b1 *
b0 &
0,
#2450
b10 $
#2500
b0 "
b11 $
1,
#2600
0,
#2700
1,
#2800
0,
#2900
b1 &
1,
#2950
b10 $
#3000
b11 $
0,
#3100
1,
#3200
0,
#3300
1,
#3400
b10 &
0,
#3450
b10 $
#3500
b0 "
b11 $
1,
#3600
0,
#3700
1,
#3800
0,
#3900
b11 &
1,
#3950
b10 $
#4000
b11 $
0,
#4100
1,
#4200
0,
#4300
1,
#4400
b10 "
b0 $
b11 *
b0 &
0,
#4450
b0 "
b10 $
#4500
b0 "
b11 $
1,
#4600
0,
#4700
1,
#4800
0,
#4900
b1 &
1,
#4950
b10 $
#5000
b11 $
0,
#5100
1,
#5200
0,
#5300
1,
#5400
b10 &
0,
#5450
b10 $
#5500
b0 "
b11 $
1,
#5600
0,
#5700
1,
#5800
0,
#5900
b11 &
1,
#5950
b10 $
#6000
b11 $
0,
#6100
1,
#6200
0,
#6300
1,
#6400
b0 $
b10 *
b0 &
0,
#6450
b10 $
#6500
b11 $
1,
#6600
0,
#6700
1,
#6800
0,
#6900
b1 &
1,
#6950
b10 $
#7000
b11 $
0,
#7100
1,
#7200
0,
#7300
1,
#7400
b10 &
0,
#7450
b10 $
#7500
b11 $
1,
#7600
0,
#7700
1,
#7800
0,
#7900
b11 &
1,
#7950
b10 $
#8000
b11 $
0,
#8100
1,
#8200
0,
#8300
1,
#8400
b0 $
b0 *
b0 &
0(
0,
#8450
b10 $
#8500
b11 $
1,
#8600
0,
#8700
1,
#8800
0,
#8900
b1 &
1,
#8950
b10 $
#9000
b11 $
0,
#9100
1,
#9200
0,
#9300
1,
#9400
b10 &
0,
#9450
b10 $
#9500
b11 $
1,
#9600
0,
#9700
1,
#9800
0,
#9900
b11 &
1,
#9950
b10 $
#10000
b11 $
0,
#10100
1,
#10200
0,
#10300
1,
#10400
b1 "
b0 $
b1 *
b0 &
0,
#10450
b10 $
#10500
b0 "
b11 $
1,
#10600
0,
#10700
1,
#10800
0,
#10900
b1 &
1,
#10950
b10 $
#11000
b11 $
0,
#11100
1,
#11200
0,
#11300
1,
#11400
b10 &
0,
#11450
b10 $
#11500
b0 "
b11 $
1,
#11600
0,
#11700
1,
#11800
0,
#11900
b11 &
1,
#11950
b10 $
#12000
b11 $
0,
#12100
1,
#12200
0,
#12300
1,
#12400
b10 "
b0 $
b11 *
b0 &
0,
#12450
b0 "
b10 $
#12500
b0 "
b11 $
1,
#12600
0,
#12700
1,
#12800
0,
#12900
b1 &
1,
#12950
b10 $
#13000
b11 $
0,
#13100
1,
#13200
0,
#13300
1,
#13400
b10 &
0,
#13450
b10 $
#13500
b0 "
b11 $
1,
#13600
0,
#13700
1,
#13800
0,
#13900
b11 &
1,
#13950
b10 $
#14000
b11 $
0,
#14100
1,
#14200
0,
#14300
1,
#14400
b0 $
b10 *
b0 &
0,
#14450
b10 $
#14500
b11 $
1,
#14600
0,
#14700
1,
#14800
0,
#14900
b1 &
1,
#14950
b10 $
#15000
b11 $
0,
#15100
1,
#15200
0,
#15300
1,
#15400
b10 &
0,
#15450
b10 $
#15500
b11 $
1,
#15600
0,
#15700
1,
#15800
0,
#15900
b11 &
1,
#15950
b10 $
#16000
b11 $
0,
#16100
1,
#16200
0,
#16300
1,
#16400
0,
b1000 )
b1 -
#16500
1,
#16600
0,
#16700
1,
#16800
b0 $
b0 *
b0 &
1(
0,
#16850
b10 $
#16900
b0 !
b11 $
1,
#17000
0,
#17100
1,
#17200
0,
#17300
b1 &
1,
#17350
b10 $
#17400
b11 $
0,
#17500
1,
#17600
0,
#17700
1,
#17800
b10 &
0,
#17850
b10 $
#17900
b0 !
b11 $
1,
#18000
0,
#18100
1,
#18200
0,
#18300
b11 &
1,
#18350
b10 $
#18400
b11 $
0,
#18500
1,
#18600
0,
#18700
1,
#18800
b1 "
b0 $
b1 *
b0 &
0,
#18850
b10 $
#18900
b0 "
b11 $
1,
#19000
0,
#19100
1,
#19200
0,
#19300
b1 &
1,
#19350
b10 $
#19400
b11 $
0,
#19500
1,
#19600
0,
#19700
1,
#19800
b10 &
0,
#19850
b10 $
#19900
b0 "
b11 $
1,
#20000
0,
#20100
1,
#20200
0,
#20300
b11 &
1,
#20350
b10 $
#20400
b11 $
0,
#20500
1,
#20600
0,
#20700
1,
#20800
b10 "
b0 $
b11 *
b0 &
0,
#20850
b0 "
b10 $
#20900
b0 "
b11 $
1,
#21000
0,
#21100
1,
#21200
0,
#21300
b1 &
1,
#21350
b10 $
#21400
b11 $
0,
#21500
1,
#21600
0,
#21700
1,
#21800
b10 &
0,
#21850
b10 $
#21900
b0 "
b11 $
1,
#22000
0,
#22100
1,
#22200
0,
#22300
b11 &
1,
#22350
b10 $
#22400
b11 $
0,
#22500
1,
#22600
0,
#22700
1,
#22800
b0 $
b10 *
b0 &
0,
#22850
b10 $
#22900
b0 !
b11 $
1,
#23000
0,
#23100
1,
#23200
0,
#23300
b1 &
1,
#23350
b10 $
#23400
b11 $
0,
#23500
1,
#23600
0,
#23700
1,
#23800
b10 &
0,
#23850
b10 $
#23900
b0 !
b11 $
1,
#24000
0,
#24100
1,
#24200
0,
#24300
b11 &
1,
#24350
b10 $
#24400
b11 $
0,
#24500
1,
#24600
0,
#24700
1,
#24800
b0 $
b0 *
b0 &
0(
0,
#24850
b10 $
#24900
b11 $
1,
#25000
0,
#25100
1,
#25200
0,
#25300
b1 &
1,
#25350
b10 $
#25400
b11 $
0,
#25500
1,
#25600
0,
#25700
1,
#25800
b10 &
0,
#25850
b10 $
#25900
b11 $
1,
#26000
0,
#26100
1,
#26200
0,
#26300
b11 &
1,
#26350
b10 $
#26400
b11 $
0,
#26500
1,
#26600
0,
#26700
1,
#26800
b1 "
b0 $
b1 *
b0 &
0,
#26850
b10 $
#26900
b0 "
b11 $
1,
#27000
0,
#27100
1,
#27200
0,
#27300
b1 &
1,
#27350
b10 $
#27400
b11 $
0,
#27500
1,
#27600
0,
#27700
1,
#27800
b10 &
0,
#27850
b10 $
#27900
b0 "
b11 $
1,
#28000
0,
#28100
1,
#28200
0,
#28300
b11 &
1,
#28350
b10 $
#28400
b11 $
0,
#28500
1,
#28600
0,
#28700
1,
#28800
b10 "
b0 $
b11 *
b0 &
0,
#28850
b0 "
b10 $
#28900
b0 "
b11 $
1,
#29000
0,
#29100
1,
#29200
0,
#29300
b1 &
1,
#29350
b10 $
#29400
b11 $
0,
#29500
1,
#29600
0,
#29700
1,
#29800
b10 &
0,
#29850
b10 $
#29900
b0 "
b11 $
1,
#30000
0,
#30100
1,
#30200
0,
#30300
b11 &
1,
#30350
b10 $
#30400
b11 $
0,
#30500
1,
#30600
0,
#30700
1,
#30800
b0 $
b10 *
b0 &
0,
#30850
b10 $
#30900
b11 $
1,
#31000
0,
#31100
1,
#31200
0,
#31300
b1 &
1,
#31350
b10 $
#31400
b11 $
0,
#31500
1,
#31600
0,
#31700
1,
#31800
b10 &
0,
#31850
b10 $
#31900
b11 $
1,
#32000
0,
#32100
1,
#32200
0,
#32300
b11 &
1,
#32350
b10 $
#32400
b11 $
0,
#32500
1,
#32600
0,
#32700
1,
#32800
0,
b100 +
b0 )
b10 -
#32900
1,
#33000
0,
#33100
1,
#33200
b0 $
b0 *
b0 &
1(
0,
#33250
b10 $
#33300
b11 $
1,
#33400
0,
#33500
1,
#33600
0,
#33700
b1 &
1,
#33750
b10 $
#33800
b11 $
0,
#33900
1,
#34000
0,
#34100
1,
#34200
b10 &
0,
#34250
b10 $
#34300
b11 $
1,
#34400
0,
#34500
1,
#34600
0,
#34700
b11 &
1,
#34750
b10 $
#34800
b11 $
0,
#34900
1,
#35000
0,
#35100
1,
#35200
b100 !
b1 "
b0 $
b1 *
b0 &
0,
#35250
b0 !
b10 $
#35300
b0 "
b0 !
b11 $
1,
#35400
0,
#35500
1,
#35600
0,
#35700
b1 &
1,
#35750
b10 $
#35800
b11 $
0,
#35900
1,
#36000
0,
#36100
1,
#36200
b10 &
0,
#36250
b10 $
#36300
b0 !
b0 "
b11 $
1,
#36400
0,
#36500
1,
#36600
0,
#36700
b11 &
1,
#36750
b10 $
#36800
b11 $
0,
#36900
1,
#37000
0,
#37100
1,
#37200
b100 !
b10 "
b0 $
b11 *
b0 &
0,
#37250
b0 !
b0 "
b10 $
#37300
b0 !
b0 "
b11 $
1,
#37400
0,
#37500
1,
#37600
0,
#37700
b1 &
1,
#37750
b10 $
#37800
b11 $
0,
#37900
1,
#38000
0,
#38100
1,
#38200
b10 &
0,
#38250
b10 $
#38300
b0 !
b0 "
b11 $
1,
#38400
0,
#38500
1,
#38600
0,
#38700
b11 &
1,
#38750
b10 $
#38800
b11 $
0,
#38900
1,
#39000
0,
#39100
1,
#39200
b0 $
b10 *
b0 &
0,
#39250
b10 $
#39300
b11 $
1,
#39400
0,
#39500
1,
#39600
0,
#39700
b1 &
1,
#39750
b10 $
#39800
b11 $
0,
#39900
1,
#40000
0,
#40100
1,
#40200
b10 &
0,
#40250
b10 $
#40300
b11 $
1,
#40400
0,
#40500
1,
#40600
0,
#40700
b11 &
1,
#40750
b10 $
#40800
b11 $
0,
#40900
1,
#41000
0,
#41100
1,
#41200
b0 $
b0 *
b0 &
0(
0,
#41250
b10 $
#41300
b11 $
1,
#41400
0,
#41500
1,
#41600
0,
#41700
b1 &
1,
#41750
b10 $
#41800
b11 $
0,
#41900
1,
#42000
0,
#42100
1,
#42200
b10 &
0,
#42250
b10 $
#42300
b11 $
1,
#42400
0,
#42500
1,
#42600
0,
#42700
b11 &
1,
#42750
b10 $
#42800
b11 $
0,
#42900
1,
#43000
0,
#43100
1,
#43200
b100 !
b1 "
b0 $
b1 *
b0 &
0,
#43250
b0 !
b10 $
#43300
b0 "
b0 !
b11 $
1,
#43400
0,
#43500
1,
#43600
0,
#43700
b1 &
1,
#43750
b10 $
#43800
b11 $
0,
#43900
1,
#44000
0,
#44100
1,
#44200
b10 &
0,
#44250
b10 $
#44300
b0 !
b0 "
b11 $
1,
#44400
0,
#44500
1,
#44600
0,
#44700
b11 &
1,
#44750
b10 $
#44800
b11 $
0,
#44900
1,
#45000
0,
#45100
1,
#45200
b100 !
b10 "
b0 $
b11 *
b0 &
0,
#45250
b0 !
b0 "
b10 $
#45300
b0 !
b0 "
b11 $
1,
#45400
0,
#45500
1,
#45600
0,
#45700
b1 &
1,
#45750
b10 $
#45800
b11 $
0,
#45900
1,
#46000
0,
#46100
1,
#46200
b10 &
0,
#46250
b10 $
#46300
b0 !
b0 "
b11 $
1,
#46400
0,
#46500
1,
#46600
0,
#46700
b11 &
1,
#46750
b10 $
#46800
b11 $
0,
#46900
1,
#47000
0,
#47100
1,
#47200
b0 $
b10 *
b0 &
0,
#47250
b10 $
#47300
b11 $
1,
#47400
0,
#47500
1,
#47600
0,
#47700
b1 &
1,
#47750
b10 $
#47800
b11 $
0,
#47900
1,
#48000
0,
#48100
1,
#48200
b10 &
0,
#48250
b10 $
#48300
b11 $
1,
#48400
0,
#48500
1,
#48600
0,
#48700
b11 &
1,
#48750
b10 $
#48800
b11 $
0,
#48900
1,
#49000
0,
#49100
1,
#49200
0,
b1000 )
b11 -
#49300
1,
#49400
0,
#49500
1,
#49600
b0 $
b0 *
b0 &
1(
0,
#49650
b10 $
#49700
b0 !
b11 $
1,
#49800
0,
#49900
1,
#50000
0,
#50100
b1 &
1,
#50150
b10 $
#50200
b11 $
0,
#50300
1,
#50400
0,
#50500
1,
#50600
b10 &
0,
#50650
b10 $
#50700
b0 !
b11 $
1,
#50800
0,
#50900
1,
#51000
0,
#51100
b11 &
1,
#51150
b10 $
#51200
b11 $
0,
#51300
1,
#51400
0,
#51500
1,
#51600
b100 !
b1 "
b0 $
b1 *
b0 &
0,
#51650
b0 !
b10 $
#51700
b0 "
b0 !
b11 $
1,
#51800
0,
#51900
1,
#52000
0,
#52100
b1 &
1,
#52150
b10 $
#52200
b11 $
0,
#52300
1,
#52400
0,
#52500
1,
#52600
b10 &
0,
#52650
b10 $
#52700
b0 !
b0 "
b11 $
1,
#52800
0,
#52900
1,
#53000
0,
#53100
b11 &
1,
#53150
b10 $
#53200
b11 $
0,
#53300
1,
#53400
0,
#53500
1,
#53600
b100 !
b10 "
b0 $
b11 *
b0 &
0,
#53650
b0 !
b0 "
b10 $
#53700
b0 !
b0 "
b11 $
1,
#53800
0,
#53900
1,
#54000
0,
#54100
b1 &
1,
#54150
b10 $
#54200
b11 $
0,
#54300
1,
#54400
0,
#54500
1,
#54600
b10 &
0,
#54650
b10 $
#54700
b0 !
b0 "
b11 $
1,
#54800
0,
#54900
1,
#55000
0,
#55100
b11 &
1,
#55150
b10 $
#55200
b11 $
0,
#55300
1,
#55400
0,
#55500
1,
#55600
b0 $
b10 *
b0 &
0,
#55650
b10 $
#55700
b0 !
b11 $
1,
#55800
0,
#55900
1,
#56000
0,
#56100
b1 &
1,
#56150
b10 $
#56200
b11 $
0,
#56300
1,
#56400
0,
#56500
1,
#56600
b10 &
0,
#56650
b10 $
#56700
b0 !
b11 $
1,
#56800
0,
#56900
1,
#57000
0,
#57100
b11 &
1,
#57150
b10 $
#57200
b11 $
0,
#57300
1,
#57400
0,
#57500
1,
#57600
b0 $
b0 *
b0 &
0(
0,
#57650
b10 $
#57700
b11 $
1,
#57800
0,
#57900
1,
#58000
0,
#58100
b1 &
1,
#58150
b10 $
#58200
b11 $
0,
#58300
1,
#58400
0,
#58500
1,
#58600
b10 &
0,
#58650
b10 $
#58700
b11 $
1,
#58800
0,
#58900
1,
#59000
0,
#59100
b11 &
1,
#59150
b10 $
#59200
b11 $
0,
#59300
1,
#59400
0,
#59500
1,
#59600
b100 !
b1 "
b0 $
b1 *
b0 &
0,
#59650
b0 !
b10 $
#59700
b0 "
b0 !
b11 $
1,
#59800
0,
#59900
1,
#60000
0,
#60100
b1 &
1,
#60150
b10 $
#60200
b11 $
0,
#60300
1,
#60400
0,
#60500
1,
#60600
b10 &
0,
#60650
b10 $
#60700
b0 !
b0 "
b11 $
1,
#60800
0,
#60900
1,
#61000
0,
#61100
b11 &
1,
#61150
b10 $
#61200
b11 $
0,
#61300
1,
#61400
0,
#61500
1,
#61600
b100 !
b10 "
b0 $
b11 *
b0 &
0,
#61650
b0 !
b0 "
b10 $
#61700
b0 !
b0 "
b11 $
1,
#61800
0,
#61900
1,
#62000
0,
#62100
b1 &
1,
#62150
b10 $
#62200
b11 $
0,
#62300
1,
#62400
0,
#62500
1,
#62600
b10 &
0,
#62650
b10 $
#62700
b0 !
b0 "
b11 $
1,
#62800
0,
#62900
1,
#63000
0,
#63100
b11 &
1,
#63150
b10 $
#63200
b11 $
0,
#63300
1,
#63400
0,
#63500
1,
#63600
b0 $
b10 *
b0 &
0,
#63650
b10 $
#63700
b11 $
1,
#63800
0,
#63900
1,
#64000
0,
#64100
b1 &
1,
#64150
b10 $
#64200
b11 $
0,
#64300
1,
#64400
0,
#64500
1,
#64600
b10 &
0,
#64650
b10 $
#64700
b11 $
1,
#64800
0,
#64900
1,
#65000
0,
#65100
b11 &
1,
#65150
b10 $
#65200
b11 $
0,
#65300
1,
#65400
0,
#65500
1,
#65600
0,
b10 %
b0 +
b0 )
b100 -
#65700
b10 !
1,
#65800
0,
#65900
1,
#66000
b0 $
b0 *
b0 &
1(
0,
#66050
b10 $
#66100
b10 !
b11 $
1,
#66200
0,
#66300
1,
#66400
0,
#66500
b1 &
1,
#66550
b10 $
#66600
b11 $
0,
#66700
1,
#66800
0,
#66900
1,
#67000
b10 &
0,
#67050
b10 $
#67100
b10 !
b11 $
1,
#67200
0,
#67300
1,
#67400
0,
#67500
b11 &
1,
#67550
b10 $
#67600
b11 $
0,
#67700
1,
#67800
0,
#67900
1,
#68000
b0 !
b1 "
b0 $
b1 *
b0 &
0,
#68050
b10 !
b10 $
#68100
b0 "
b10 !
b11 $
1,
#68200
0,
#68300
1,
#68400
0,
#68500
b1 &
1,
#68550
b10 $
#68600
b11 $
0,
#68700
1,
#68800
0,
#68900
1,
#69000
b10 &
0,
#69050
b10 $
#69100
b10 !
b0 "
b11 $
1,
#69200
0,
#69300
1,
#69400
0,
#69500
b11 &
1,
#69550
b10 $
#69600
b11 $
0,
#69700
1,
#69800
0,
#69900
1,
#70000
b0 !
b10 "
b0 $
b11 *
b0 &
0,
#70050
b10 !
b0 "
b10 $
#70100
b10 !
b0 "
b11 $
1,
#70200
0,
#70300
1,
#70400
0,
#70500
b1 &
1,
#70550
b10 $
#70600
b11 $
0,
#70700
1,
#70800
0,
#70900
1,
#71000
b10 &
0,
#71050
b10 $
#71100
b10 !
b0 "
b11 $
1,
#71200
0,
#71300
1,
#71400
0,
#71500
b11 &
1,
#71550
b10 $
#71600
b11 $
0,
#71700
1,
#71800
0,
#71900
1,
#72000
b0 $
b10 *
b0 &
0,
#72050
b10 $
#72100
b10 !
b11 $
1,
#72200
0,
#72300
1,
#72400
0,
#72500
b1 &
1,
#72550
b10 $
#72600
b11 $
0,
#72700
1,
#72800
0,
#72900
1,
#73000
b10 &
0,
#73050
b10 $
#73100
b10 !
b11 $
1,
#73200
0,
#73300
1,
#73400
0,
#73500
b11 &
1,
#73550
b10 $
#73600
b11 $
0,
#73700
1,
#73800
0,
#73900
1,
#74000
b0 $
b0 *
b0 &
0(
0,
#74050
b10 $
#74100
b11 $
1,
#74200
0,
#74300
1,
#74400
0,
#74500
b1 &
1,
#74550
b10 $
#74600
b11 $
0,
#74700
1,
#74800
0,
#74900
1,
#75000
b10 &
0,
#75050
b10 $
#75100
b11 $
1,
#75200
0,
#75300
1,
#75400
0,
#75500
b11 &
1,
#75550
b10 $
#75600
b11 $
0,
#75700
1,
#75800
0,
#75900
1,
#76000
b0 !
b1 "
b0 $
b1 *
b0 &
0,
#76050
b10 !
b10 $
#76100
b0 "
b10 !
b11 $
1,
#76200
0,
#76300
1,
#76400
0,
#76500
b1 &
1,
#76550
b10 $
#76600
b11 $
0,
#76700
1,
#76800
0,
#76900
1,
#77000
b10 &
0,
#77050
b10 $
#77100
b10 !
b0 "
b11 $
1,
#77200
0,
#77300
1,
#77400
0,
#77500
b11 &
1,
#77550
b10 $
#77600
b11 $
0,
#77700
1,
#77800
0,
#77900
1,
#78000
b0 !
b10 "
b0 $
b11 *
b0 &
0,
#78050
b10 !
b0 "
b10 $
#78100
b10 !
b0 "
b11 $
1,
#78200
0,
#78300
1,
#78400
0,
#78500
b1 &
1,
#78550
b10 $
#78600
b11 $
0,
#78700
1,
#78800
0,
#78900
1,
#79000
b10 &
0,
#79050
b10 $
#79100
b10 !
b0 "
b11 $
1,
#79200
0,
#79300
1,
#79400
0,
#79500
b11 &
1,
#79550
b10 $
#79600
b11 $
0,
#79700
1,
#79800
0,
#79900
1,
#80000
b0 $
b10 *
b0 &
0,
#80050
b10 $
#80100
b11 $
1,
#80200
0,
#80300
1,
#80400
0,
#80500
b1 &
1,
#80550
b10 $
#80600
b11 $
0,
#80700
1,
#80800
0,
#80900
1,
#81000
b10 &
0,
#81050
b10 $
#81100
b11 $
1,
#81200
0,
#81300
1,
#81400
0,
#81500
b11 &
1,
#81550
b10 $
#81600
b11 $
0,
#81700
1,
#81800
0,
#81900
1,
#82000
0,
b1000 )
b101 -
#82100
1,
#82200
0,
#82300
1,
#82400
b0 $
b0 *
b0 &
1(
0,
#82450
b10 $
#82500
b10 !
b11 $
1,
#82600
0,
#82700
1,
#82800
0,
#82900
b1 &
1,
#82950
b10 $
#83000
b11 $
0,
#83100
1,
#83200
0,
#83300
1,
#83400
b10 &
0,
#83450
b10 $
#83500
b10 !
b11 $
1,
#83600
0,
#83700
1,
#83800
0,
#83900
b11 &
1,
#83950
b10 $
#84000
b11 $
0,
#84100
1,
#84200
0,
#84300
1,
#84400
b0 !
b1 "
b0 $
b1 *
b0 &
0,
#84450
b10 !
b10 $
#84500
b0 "
b10 !
b11 $
1,
#84600
0,
#84700
1,
#84800
0,
#84900
b1 &
1,
#84950
b10 $
#85000
b11 $
0,
#85100
1,
#85200
0,
#85300
1,
#85400
b10 &
0,
#85450
b10 $
#85500
b10 !
b0 "
b11 $
1,
#85600
0,
#85700
1,
#85800
0,
#85900
b11 &
1,
#85950
b10 $
#86000
b11 $
0,
#86100
1,
#86200
0,
#86300
1,
#86400
b0 !
b10 "
b0 $
b11 *
b0 &
0,
#86450
b10 !
b0 "
b10 $
#86500
b10 !
b0 "
b11 $
1,
#86600
0,
#86700
1,
#86800
0,
#86900
b1 &
1,
#86950
b10 $
#87000
b11 $
0,
#87100
1,
#87200
0,
#87300
1,
#87400
b10 &
0,
#87450
b10 $
#87500
b10 !
b0 "
b11 $
1,
#87600
0,
#87700
1,
#87800
0,
#87900
b11 &
1,
#87950
b10 $
#88000
b11 $
0,
#88100
1,
#88200
0,
#88300
1,
#88400
b0 $
b10 *
b0 &
0,
#88450
b10 $
