tests/testfiles/ift/test_cells/sr/sr_ift.v
/* Generated by Yosys 0.20 (git sha1 4fcb95ed087, clang  -fPIC -Os) */

(* dynports =  1  *)
(* src = "dlatch.v:1.1-15.10" *)
module m_0(CLR,CLR_t,SET, SET_t, Q, Q_t);
  (* src = "dlatch.v:7.19-7.20" *)
  input [1:0] CLR;
  wire [1:0] CLR;
  (* src = "dlatch.v:8.24-8.25" *)
  output [1:0] Q;
  reg [1:0] Q;
  (* src = "dlatch.v:6.7-6.9" *)
  input [1:0] SET;
  wire [1:0] SET;
  
  input wire [31:0] CLR_t;
  input wire [31:0] SET_t;
  output reg [31:0] Q_t = 0;
  (* src = "dlatch.v:10.1-13.4" *)
  always @*
    if (CLR[0])begin
     Q[0] <= 1'b0;
     Q_t <= CLR_t;
     end
    else if (SET[0])begin
     Q[0] <= 1'b1;
     Q_t <= SET_t;
     end
  (* src = "dlatch.v:10.1-13.4" *)
  always @*
    if (CLR[1])begin
     Q[1] <= 1'b0;
     Q_t <= CLR_t;
     end
    else if (SET[1])begin
     Q[1] <= 1'b1;
     Q_t <= SET_t;
     end
endmodule

tests/testfiles/ift/test_cells/sr/sr_ift_tb.v
`timescale 1us/100ns
module sr_tb();
	reg [1:0] SET;
	reg [1:0] CLR;
	wire[1:0] Q;
	
	reg [31:0] SET_t;
	reg [31:0] CLR_t;
	wire [31:0] Q_t;


	reg[63:0] read_data [0:3];
	integer i;
	
	m_0 d1(.CLR(CLR),.CLR_t(CLR_t), .Q(Q), .Q_t(Q_t), .SET(SET), .SET_t(SET_t));

	initial begin 
		$readmemb(`INPUT_FILE_NAME, read_data);
		for(i = 0; i<=3; i+=1) begin
		{ CLR_t,SET_t} = read_data[i]; 
		 #40;
		 SET <= 'b00;
		 CLR <= 'b00;
		 #5;
		 CLR <= 'b10;
		 #5;
		 CLR <= 'b11;
		 #40;
		 SET <= 'b01;
		 CLR <= 'b00;
		 #5;
		 CLR <= 'b10;
		 #5;
		 CLR <= 'b11;
		 #40;
		 SET <= 'b11;
		 CLR <= 'b00;
		 #5;
		 CLR <= 'b10;
		 #5;
		 CLR <= 'b11;
		 #40;
		 SET <= 'b10;
		 CLR <= 'b00;
		 #5;
		 CLR <= 'b10;
		 #5;
		 CLR <= 'b11;
		 #40;
		 end
		 $finish;
	end
	initial
	begin
		$dumpfile(`DUMP_FILE_NAME);
		//$dumpfile("sr.vcd");
		$dumpvars(1);		//writing the vcd file
	end
 	
endmodule

tests/testfiles/ift/test_cells/sr/sr_ift.vcd
$date
	Tue Jan 16 14:38:52 2024
$end
$version
	Icarus Verilog
$end
$timescale
	100ns
$end
$scope module sr_tb $end
$var wire 32 ! Q_t [31:0] $end
$var wire 2 " Q [1:0] $end
$var reg 2 # CLR [1:0] $end
$var reg 32 $ CLR_t [31:0] $end
$var reg 2 % SET [1:0] $end
$var reg 32 & SET_t [31:0] $end
$var integer 32 ' i [31:0] $end
$upscope $end
$enddefinitions $end
$comment Show the parameter values. $end
$dumpall
$end
#0
$dumpvars
b0 '
b10 &
bx %
b1 $
bx #
bx "
b0 !
$end
#400
b0 #
b0 %
#450
b1 !
b0x "
b10 #
#500
b0 "
b11 #
#900
b10 !
b1 "
b0 #
b1 %
#950
b10 !
b10 #
#1000
b1 !
b0 "
b11 #
#1400
b10 !
b11 "
b0 #
b11 %
#1450
b1 !
b1 "
b10 #
#1500
b0 "
b11 #
#1900
b10 !
b10 "
b0 #
b10 %
#1950
b1 !
b0 "
b10 #
#2000
b11 #
#2400
b0 &
b1 '
#2800
b0 #
b0 %
#2850
b10 #
#2900
b11 #
#3300
b0 !
b1 "
b0 #
b1 %
#3350
b1 !
b10 #
#3400
b0 "
b11 #
#3800
b0 !
b11 "
b0 #
b11 %
#3850
b0 !
b1 "
b10 #
#3900
b1 !
b0 "
b11 #
#4300
b0 !
b10 "
b0 #
b10 %
#4350
b1 !
b0 "
b10 #
#4400
b11 #
#4800
b0 !
b0 $
b10 &
b10 '
#5200
b0 #
b0 %
#5250
b10 #
#5300
b11 #
#5700
b10 !
b1 "
b0 #
b1 %
#5750
b10 !
b10 #
#5800
b0 !
b0 "
b11 #
#6200
b10 !
b11 "
b0 #
b11 %
#6250
b0 !
b1 "
b10 #
#6300
b0 "
b11 #
#6700
b10 !
b10 "
b0 #
b10 %
#6750
b0 !
b0 "
b10 #
#6800
b11 #
#7200
b0 &
b11 '
#7600
b0 #
b0 %
#7650
b10 #
#7700
b11 #
#8100
b1 "
b0 #
b1 %
#8150
b10 #
#8200
b0 "
b11 #
#8600
b11 "
b0 #
b11 %
#8650
b1 "
b10 #
#8700
b0 "
b11 #
#9100
b10 "
b0 #
b10 %
#9150
b0 "
b10 #
#9200
b11 #
#9600
b100 '
