tests/testfiles/counter_ift/counter_ift.v
module counter( clk, clk_t, rst, rst_t, en, en_t, count, count_t);

	input clk, rst, en;
	input [31:0] clk_t;
	input [31:0] rst_t;
	input [31:0] en_t;
	output reg[3:0] count;
	output reg[31:0] count_t;

	initial begin
	    count_t = 0;
	end

	always @(posedge clk)
		if (rst) begin
			count <= 4'd0;
			count_t <= rst_t;
	    end else if (en) begin
			count <= count + 4'd1;
			count_t <= count_t | en_t;
        end
endmodule

tests/testfiles/counter_ift/counter_ift_tb.v
module counter_tb;

	/* make a reset that pulses once. */
	reg rst = 0;
	reg [31:0] rst_t = 0;
	reg [31:0] en_t = 0;
	reg [31:0] clk_t = 0;
	
	reg [95:0] read_data [0:95];
   	integer i, t;
   
	initial begin
		# 12 rst = 1;
		# 16 rst = 0;
		# 20 rst = 1;
		# 12 rst = 0;
		# 300 $finish;
	end

  initial begin
      $readmemb(`INPUT_FILE_NAME, read_data);
      for(i = 0; i<=4; i++) begin
      {rst_t, en_t, t} =  read_data[i];
      #t;
      end
   end

	/* Make a regular pulsing clock. */
	reg clk = 0;
	always #2 clk = !clk;
	wire [3:0] count;
	wire [31:0] count_t;
	reg en = 1;

	//timesteps to clock frequency

	always #8 en= $time % 3;
	// instance of the counter module
	counter c1 ( .clk(clk), .clk_t(clk_t), .rst(rst), .rst_t(rst_t), .en(en), .en_t(en_t), .count(count), .count_t(count_t));
	
	initial
		begin
			$dumpfile(`DUMP_FILE_NAME);
			$dumpvars;		//writing the vcd file
		end
	
	//initial
		//$monitor("At time %t, clk %d, rst %d, en %d, count %d", $time, clk, rst, en, count);
endmodule // test

tests/testfiles/counter_ift/counter_ift.vcd
$date
	Thu Feb  1 11:51:05 2024
$end
$version
	Icarus Verilog
$end
$timescale
	1s
$end
$scope module counter_tb $end
$var wire 32 ! count_t [31:0] $end
$var wire 4 " count [3:0] $end
$var reg 1 # clk $end
$var reg 32 $ clk_t [31:0] $end
$var reg 1 % en $end
$var reg 32 & en_t [31:0] $end
$var reg 1 ' rst $end
$var reg 32 ( rst_t [31:0] $end
$var integer 32 ) i [31:0] $end
$var integer 32 * t [31:0] $end
$scope module c1 $end
$var wire 1 # clk $end
$var wire 32 + clk_t [31:0] $end
$var wire 1 % en $end
$var wire 32 , en_t [31:0] $end
$var wire 1 ' rst $end
$var wire 32 - rst_t [31:0] $end
$var reg 4 . count [3:0] $end
$var reg 32 / count_t [31:0] $end
$upscope $end
$upscope $end
$enddefinitions $end
$comment Show the parameter values. $end
$dumpall
$end
#0
$dumpvars
b0 /
bx .
b0 -
b0 ,
b0 +
b1100 *
b0 )
b0 (
0'
b0 &
1%
b0 $
0#
bx "
b0 !
$end
#2
1#
#4
0#
#6
1#
#8
0#
0%
#10
1#
#12
0#
b1 &
b1 ,
b10000000 *
b1 )
1'
#14
b0 "
b0 .
1#
#16
0#
1%
#18
1#
#20
0#
#22
1#
#24
0#
0%
#26
1#
#28
0#
0'
#30
1#
#32
0#
#34
1#
#36
0#
#38
1#
#40
0#
1%
#42
b1 !
b1 /
b1 "
b1 .
1#
#44
0#
#46
b10 "
b10 .
1#
#48
0#
0%
1'
#50
b0 !
b0 /
b0 "
b0 .
1#
#52
0#
#54
1#
#56
0#
#58
1#
#60
0#
0'
#62
1#
#64
0#
1%
#66
b1 !
b1 /
b1 "
b1 .
1#
#68
0#
#70
b10 "
b10 .
1#
#72
0#
0%
#74
1#
#76
0#
#78
1#
#80
0#
#82
1#
#84
0#
#86
1#
#88
0#
1%
#90
b11 "
b11 .
1#
#92
0#
#94
b100 "
b100 .
1#
#96
0#
0%
#98
1#
#100
0#
#102
1#
#104
0#
#106
1#
#108
0#
#110
1#
#112
0#
1%
#114
b101 "
b101 .
1#
#116
0#
#118
b110 "
b110 .
1#
#120
0#
0%
#122
1#
#124
0#
#126
1#
#128
0#
#130
1#
#132
0#
#134
1#
#136
0#
1%
#138
b111 "
b111 .
1#
#140
0#
b10 (
b10 -
b0 &
b0 ,
b1000 *
b10 )
#142
b1000 "
b1000 .
1#
#144
0#
0%
#146
1#
#148
0#
b1 &
b1 ,
b11 )
#150
1#
#152
0#
#154
1#
#156
0#
b0 (
b0 -
b0 &
b0 ,
b100 )
#158
1#
#160
0#
1%
#162
b1001 "
b1001 .
1#
#164
0#
b101 )
#166
b1010 "
b1010 .
1#
#168
0#
0%
#170
1#
#172
0#
#174
1#
#176
0#
#178
1#
#180
0#
#182
1#
#184
0#
1%
#186
b1011 "
b1011 .
1#
#188
0#
#190
b1100 "
b1100 .
1#
#192
0#
0%
#194
1#
#196
0#
#198
1#
#200
0#
#202
1#
#204
0#
#206
1#
#208
0#
1%
#210
b1101 "
b1101 .
1#
#212
0#
#214
b1110 "
b1110 .
1#
#216
0#
0%
#218
1#
#220
0#
#222
1#
#224
0#
#226
1#
#228
0#
#230
1#
#232
0#
1%
#234
b1111 "
b1111 .
1#
#236
0#
#238
b0 "
b0 .
1#
#240
0#
0%
#242
1#
#244
0#
#246
1#
#248
0#
#250
1#
#252
0#
#254
1#
#256
0#
1%
#258
b1 "
b1 .
1#
#260
0#
#262
b10 "
b10 .
1#
#264
0#
0%
#266
1#
#268
0#
#270
1#
#272
0#
#274
1#
#276
0#
#278
1#
#280
0#
1%
#282
b11 "
b11 .
1#
#284
0#
#286
b100 "
b100 .
1#
#288
0#
0%
#290
1#
#292
0#
#294
1#
#296
0#
#298
1#
#300
0#
#302
1#
#304
0#
1%
#306
b101 "
b101 .
1#
#308
0#
#310
b110 "
b110 .
1#
#312
0#
0%
#314
1#
#316
0#
#318
1#
#320
0#
#322
1#
#324
0#
#326
1#
#328
0#
1%
#330
b111 "
b111 .
1#
#332
0#
#334
b1000 "
b1000 .
1#
#336
0#
0%
#338
1#
#340
0#
#342
1#
#344
0#
#346
1#
#348
0#
#350
1#
#352
0#
1%
#354
b1001 "
b1001 .
1#
#356
0#
#358
b1010 "
b1010 .
1#
