tests/testfiles/ift/flipFlops/adff/adff_ift.v
module m_0(ARST, ARST_t, CLK, CLK_t, D, D_t, Q, Q_t);

parameter WIDTH = 2;
parameter CLK_POLARITY = 1'b1;
parameter ARST_POLARITY = 1'b1;
parameter ARST_VALUE = 2;

input CLK, ARST;
input [WIDTH-1:0] D;
input [31:0] CLK_t;
input [31:0] ARST_t;
input [31:0] D_t;
output reg [WIDTH-1:0] Q;
output reg [31:0] Q_t;
wire pos_clk = CLK == CLK_POLARITY;
wire pos_arst = ARST == ARST_POLARITY;

initial begin
    Q_t = 0;
end

always @(posedge pos_clk, posedge pos_arst) begin
	if (pos_arst)begin
		Q <= ARST_VALUE;
		Q_t <= (^D === 1'bx) ? 0 : ((D == ARST_VALUE) ? (D_t | ARST_t) : ARST_t);
	end
	else begin
		Q <= D;
		Q_t <= (^D === 1'bx) ? 0 : ((D == ARST_VALUE) ? (D_t | ARST_t) : D_t);
	end
end


endmodule

tests/testfiles/ift/flipFlops/adff/adff_ift_tb.v
`timescale 1ns/1ps
module adff_tb();
	reg [1:0] D;
	reg CLK;
	wire[1:0] Q;
	reg ARST;
	
	reg [31:0] D_t;
	reg [31:0] CLK_t = 0;
	reg [31:0] ARST_t;
	wire [31:0] Q_t;
	
	reg[63:0] read_data [0:3];
	integer i;

	m_0 d1(ARST, ARST_t, CLK, CLK_t, D, D_t, Q, Q_t);

	initial begin
  		CLK=0;
     		forever #10 CLK = ~CLK;  
	end 

	initial begin 
		$readmemb(`INPUT_FILE_NAME, read_data);
		
		for(i = 0; i<4; i+=1) begin
		{ARST_t, D_t} = read_data[i];
		 #40;
		 D <= 'b00;
		 #5;
		 ARST <= 1;
		 #5;
		 ARST <= 0;
		 #40;
		 D <= 'b01;
		 #5;
		 ARST <= 1;
		 #5;
		 ARST <= 0;
		 #40;
		 D <= 'b10;
		 #5;
		 ARST <= 1;
		 #5;
		 ARST <= 0;
		 #40;
		 D <= 'b11;
		 #5;
		 ARST <= 1;
		 #5;
		 ARST <= 0;
		 #40;
		 end
		 $finish;
	end
	initial
	begin
		$dumpfile(`DUMP_FILE_NAME);
		$dumpvars(1);		//writing the vcd file
	end
 	
endmodule

tests/testfiles/ift/flipFlops/adff/adff_ift.vcd
$date
	Mon Feb  5 16:42:00 2024
$end
$version
	Icarus Verilog
$end
$timescale
	1ps
$end
$scope module adff_tb $end
$var wire 32 ! Q_t [31:0] $end
$var wire 2 " Q [1:0] $end
$var reg 1 # ARST $end
$var reg 32 $ ARST_t [31:0] $end
$var reg 1 % CLK $end
$var reg 32 & CLK_t [31:0] $end
$var reg 2 ' D [1:0] $end
$var reg 32 ( D_t [31:0] $end
$var integer 32 ) i [31:0] $end
$upscope $end
$enddefinitions $end
$comment Show the parameter values. $end
$dumpall
$end
#0
$dumpvars
b0 )
b10 (
bx '
b0 &
0%
b1 $
x#
bx "
b0 !
$end
#10000
1%
#20000
0%
#30000
1%
#40000
b0 '
0%
#45000
b1 !
b10 "
1#
#50000
0#
1%
#60000
0%
#70000
b10 !
b0 "
1%
#80000
0%
#90000
b1 '
1%
#95000
b1 !
b10 "
1#
#100000
0#
0%
#110000
b10 !
b1 "
1%
#120000
0%
#130000
1%
#140000
b10 '
0%
#145000
b11 !
b10 "
1#
#150000
0#
1%
#160000
0%
#170000
1%
#180000
0%
#190000
b11 '
1%
#195000
b1 !
1#
#200000
0#
0%
#210000
b10 !
b11 "
1%
#220000
0%
#230000
1%
#240000
0%
b0 (
b1 )
#250000
b0 !
1%
#260000
0%
#270000
1%
#280000
b0 '
0%
#285000
b1 !
b10 "
1#
#290000
0#
1%
#300000
0%
#310000
b0 !
b0 "
1%
#320000
0%
#330000
b1 '
1%
#335000
b1 !
b10 "
1#
#340000
0#
0%
#350000
b0 !
b1 "
1%
#360000
0%
#370000
1%
#380000
b10 '
0%
#385000
b1 !
b10 "
1#
#390000
0#
1%
#400000
0%
#410000
1%
#420000
0%
#430000
b11 '
1%
#435000
1#
#440000
0#
0%
#450000
b0 !
b11 "
1%
#460000
0%
#470000
1%
#480000
0%
b0 $
b10 )
#490000
1%
#500000
0%
#510000
1%
#520000
b0 '
0%
#525000
b10 "
1#
#530000
0#
1%
#540000
0%
#550000
b0 "
1%
#560000
0%
#570000
b1 '
1%
#575000
b10 "
1#
#580000
0#
0%
#590000
b1 "
1%
#600000
0%
#610000
1%
#620000
b10 '
0%
#625000
b10 "
1#
#630000
0#
1%
#640000
0%
#650000
1%
#660000
0%
#670000
b11 '
1%
#675000
1#
#680000
0#
0%
#690000
b11 "
1%
#700000
0%
#710000
1%
#720000
0%
b10 (
b11 )
#730000
b10 !
1%
#740000
0%
#750000
1%
#760000
b0 '
0%
#765000
b0 !
b10 "
1#
#770000
0#
1%
#780000
0%
#790000
b10 !
b0 "
1%
#800000
0%
#810000
b1 '
1%
#815000
b0 !
b10 "
1#
#820000
0#
0%
#830000
b10 !
b1 "
1%
#840000
0%
#850000
1%
#860000
b10 '
0%
#865000
b10 "
1#
#870000
0#
1%
#880000
0%
#890000
1%
#900000
0%
#910000
b11 '
1%
#915000
b0 !
1#
#920000
0#
0%
#930000
b10 !
b11 "
1%
#940000
0%
#950000
1%
#960000
0%
b100 )
