tests/testfiles/ift/test_cells/pmux_ue/pmux_ue_ift.v
/* Generated by Yosys 0.20 (git sha1 4fcb95ed087, clang  -fPIC -Os) */

(* dynports =  1  *)
(* src = "mux.v:1.1-16.10" *)
module m_0 (A,A_t, B, B_t, S,S_t, Y,Y_t);
  (* src = "mux.v:5.23-5.24" *)
  input [1:0] A;
  wire [1:0] A;
  (* src = "mux.v:5.26-5.27" *)
  input [5:0] B;
  wire [5:0] B;
  (* src = "mux.v:6.11-6.12" *)
  input [2:0] S;
  wire [2:0] S;
  (* src = "mux.v:7.28-7.29" *)
  output [1:0] Y;
  wire [1:0] Y;
    input wire [31:0] A_t;
  input wire [31:0] B_t;
  input wire [31:0] S_t;
  output wire [31:0] Y_t;
  
  function [1:0] _0_;
    input [1:0] a;
    input [5:0] b;
    input [2:0] s;
    (* full_case = 32'd1 *)
    (* parallel_case = 32'd1 *)
    (* src = "mux.v:10.13-10.14|mux.v:10.9-13.19" *)
    (* parallel_case *)
    casez (s)
      3'b??1:
        _0_ = b[1:0];
      3'b?1?:
        _0_ = b[3:2];
      3'b1??:
        _0_ = b[5:4];
      default:
        _0_ = a;
    endcase
  endfunction
      function [31:0] _1_;
    input [31:0] a_t;
    input [31:0] b_t;
    input [31:0] s_t;
    input [2:0] s;
    (* full_case = 32'd1 *)
    (* parallel_case = 32'd1 *)
    (* src = "mux.v:10.13-10.14|mux.v:10.9-13.19" *)
    (* parallel_case *)
    casez (s)
        3'b??1:
        _1_ = (^s === 1'bx) ? 0 : (b_t | s_t);
      3'b?1?:
       _1_ = (^s === 1'bx) ? 0 : (b_t | s_t);
      3'b1??:
        _1_ = (^s === 1'bx) ? 0 : (b_t | s_t);
      default:
        _1_ = (^s === 1'bx) ? 0 : (a_t | s_t);
    endcase
  endfunction
  assign Y = _0_(A, B, S);
  assign Y_t = _1_(A_t, B_t, S_t,S);
endmodule

tests/testfiles/ift/test_cells/pmux_ue/pmux_ue_ift_tb.v
`timescale 1us/100ns
module pmux_ue_tb();
	reg [1:0] A;
	reg [5:0] B;
	reg [2:0] S;
	wire[1:0] Y;
	
	reg[31:0] A_t;
	reg[31:0] B_t;
	reg[31:0] S_t;
	wire[31:0] Y_t;
	
	reg[95:0] read_data [0:7];
	integer i;

	m_0 d1(.A(A),.A_t(A_t),.B(B),.B_t(B_t),.S(S),.S_t(S_t),.Y(Y),.Y_t(Y_t));

	initial begin 
		$readmemb(`INPUT_FILE_NAME, read_data);
		for(i = 0; i<=7; i+=1) begin
		{ A_t,B_t,S_t} = read_data[i]; 
		#5;
		 A <= 0;
		 B <= 0;
		 S <= 0;
		 #5;
		 A <= 0;
		 B <= 0;
		 S <= 1;
		 #5;
		 A <= 0;
		 B <= 0;
		 S <= 2;
		 #5;
		 A <= 0;
		 B <= 0;
		 S <= 3;
		 #5;
		 A <= 0;
		 B <= 0;
		 S <= 4;
		 #5;
		 A <= 0;
		 B <= 0;
		 S <= 5;
		 #5;
		 A <= 0;
		 B <= 0;
		 S <= 6;
		 #5;
		 A <= 0;
		 B <= 19;
		 S <= 0;
		 #5;
		 A <= 0;
		 B <= 19;
		 S <= 1;
		 #5;
		 A <= 0;
		 B <= 19;
		 S <= 2;
		 #5;
		 A <= 0;
		 B <= 19;
		 S <= 3;
		 #5;
		 A <= 0;
		 B <= 19;
		 S <= 4;
		 #5;
		 A <= 0;
		 B <= 19;
		 S <= 5;
		 #5;
		 A <= 0;
		 B <= 19;
		 S <= 6;
		 #5;
		 A <= 0;
		 B <= 38;
		 S <= 0;
		 #5;
		 A <= 0;
		 B <= 38;
		 S <= 1;
		 #5;
		 A <= 0;
		 B <= 38;
		 S <= 2;
		 #5;
		 A <= 0;
		 B <= 38;
		 S <= 3;
		 #5;
		 A <= 0;
		 B <= 38;
		 S <= 4;
		 #5;
		 A <= 0;
		 B <= 38;
		 S <= 5;
		 #5;
		 A <= 0;
		 B <= 38;
		 S <= 6;
		 #5;
		 A <= 0;
		 B <= 57;
		 S <= 0;
		 #5;
		 A <= 0;
		 B <= 57;
		 S <= 1;
		 #5;
		 A <= 0;
		 B <= 57;
		 S <= 2;
		 #5;
		 A <= 0;
		 B <= 57;
		 S <= 3;
		 #5;
		 A <= 0;
		 B <= 57;
		 S <= 4;
		 #5;
		 A <= 0;
		 B <= 57;
		 S <= 5;
		 #5;
		 A <= 0;
		 B <= 57;
		 S <= 6;
		 #5;
		 A <= 1;
		 B <= 0;
		 S <= 0;
		 #5;
		 A <= 1;
		 B <= 0;
		 S <= 1;
		 #5;
		 A <= 1;
		 B <= 0;
		 S <= 2;
		 #5;
		 A <= 1;
		 B <= 0;
		 S <= 3;
		 #5;
		 A <= 1;
		 B <= 0;
		 S <= 4;
		 #5;
		 A <= 1;
		 B <= 0;
		 S <= 5;
		 #5;
		 A <= 1;
		 B <= 0;
		 S <= 6;
		 #5;
		 A <= 1;
		 B <= 19;
		 S <= 0;
		 #5;
		 A <= 1;
		 B <= 19;
		 S <= 1;
		 #5;
		 A <= 1;
		 B <= 19;
		 S <= 2;
		 #5;
		 A <= 1;
		 B <= 19;
		 S <= 3;
		 #5;
		 A <= 1;
		 B <= 19;
		 S <= 4;
		 #5;
		 A <= 1;
		 B <= 19;
		 S <= 5;
		 #5;
		 A <= 1;
		 B <= 19;
		 S <= 6;
		 #5;
		 A <= 1;
		 B <= 38;
		 S <= 0;
		 #5;
		 A <= 1;
		 B <= 38;
		 S <= 1;
		 #5;
		 A <= 1;
		 B <= 38;
		 S <= 2;
		 #5;
		 A <= 1;
		 B <= 38;
		 S <= 3;
		 #5;
		 A <= 1;
		 B <= 38;
		 S <= 4;
		 #5;
		 A <= 1;
		 B <= 38;
		 S <= 5;
		 #5;
		 A <= 1;
		 B <= 38;
		 S <= 6;
		 #5;
		 A <= 1;
		 B <= 57;
		 S <= 0;
		 #5;
		 A <= 1;
		 B <= 57;
		 S <= 1;
		 #5;
		 A <= 1;
		 B <= 57;
		 S <= 2;
		 #5;
		 A <= 1;
		 B <= 57;
		 S <= 3;
		 #5;
		 A <= 1;
		 B <= 57;
		 S <= 4;
		 #5;
		 A <= 1;
		 B <= 57;
		 S <= 5;
		 #5;
		 A <= 1;
		 B <= 57;
		 S <= 6;
		 #5;
		 A <= 2;
		 B <= 0;
		 S <= 0;
		 #5;
		 A <= 2;
		 B <= 0;
		 S <= 1;
		 #5;
		 A <= 2;
		 B <= 0;
		 S <= 2;
		 #5;
		 A <= 2;
		 B <= 0;
		 S <= 3;
		 #5;
		 A <= 2;
		 B <= 0;
		 S <= 4;
		 #5;
		 A <= 2;
		 B <= 0;
		 S <= 5;
		 #5;
		 A <= 2;
		 B <= 0;
		 S <= 6;
		 #5;
		 A <= 2;
		 B <= 19;
		 S <= 0;
		 #5;
		 A <= 2;
		 B <= 19;
		 S <= 1;
		 #5;
		 A <= 2;
		 B <= 19;
		 S <= 2;
		 #5;
		 A <= 2;
		 B <= 19;
		 S <= 3;
		 #5;
		 A <= 2;
		 B <= 19;
		 S <= 4;
		 #5;
		 A <= 2;
		 B <= 19;
		 S <= 5;
		 #5;
		 A <= 2;
		 B <= 19;
		 S <= 6;
		 #5;
		 A <= 2;
		 B <= 38;
		 S <= 0;
		 #5;
		 A <= 2;
		 B <= 38;
		 S <= 1;
		 #5;
		 A <= 2;
		 B <= 38;
		 S <= 2;
		 #5;
		 A <= 2;
		 B <= 38;
		 S <= 3;
		 #5;
		 A <= 2;
		 B <= 38;
		 S <= 4;
		 #5;
		 A <= 2;
		 B <= 38;
		 S <= 5;
		 #5;
		 A <= 2;
		 B <= 38;
		 S <= 6;
		 #5;
		 A <= 2;
		 B <= 57;
		 S <= 0;
		 #5;
		 A <= 2;
		 B <= 57;
		 S <= 1;
		 #5;
		 A <= 2;
		 B <= 57;
		 S <= 2;
		 #5;
		 A <= 2;
		 B <= 57;
		 S <= 3;
		 #5;
		 A <= 2;
		 B <= 57;
		 S <= 4;
		 #5;
		 A <= 2;
		 B <= 57;
		 S <= 5;
		 #5;
		 A <= 2;
		 B <= 57;
		 S <= 6;
		 end

		 $finish;
	end
	initial
	begin
		$dumpfile(`DUMP_FILE_NAME);
		//$dumpfile("pmux_ue.vcd");
		$dumpvars(1);		//writing the vcd file
	end
 	
endmodule

tests/testfiles/ift/test_cells/pmux_ue/pmux_ue_ift.vcd
$date
	Thu Mar 21 10:52:06 2024
$end
$version
	Icarus Verilog
$end
$timescale
	100ns
$end
$scope module pmux_ue_tb $end
$var wire 32 ! Y_t [31:0] $end
$var wire 2 " Y [1:0] $end
$var reg 2 # A [1:0] $end
$var reg 32 $ A_t [31:0] $end
$var reg 6 % B [5:0] $end
$var reg 32 & B_t [31:0] $end
$var reg 3 ' S [2:0] $end
$var reg 32 ( S_t [31:0] $end
$var integer 32 ) i [31:0] $end
$upscope $end
$enddefinitions $end
$comment Show the parameter values. $end
$dumpall
$end
#0
$dumpvars
b0 )
b100 (
bx '
b10 &
bx %
b1 $
bx #
bx "
b101 !
$end
#50
b0 "
b0 '
b0 %
b0 #
#100
b110 !
b1 '
#150
b10 '
#200
b11 '
#250
b100 '
#300
b101 '
#350
b110 '
#400
b101 !
b0 '
b10011 %
#450
b110 !
b11 "
b1 '
#500
b0 "
b10 '
#550
b11 "
b11 '
#600
b1 "
b100 '
#650
b11 "
b101 '
#700
b0 "
b110 '
#750
b101 !
b0 '
b100110 %
#800
b110 !
b10 "
b1 '
#850
b1 "
b10 '
#900
b10 "
b11 '
#950
b100 '
#1000
b101 '
#1050
b1 "
b110 '
#1100
b101 !
b0 "
b0 '
b111001 %
#1150
b110 !
b1 "
b1 '
#1200
b10 "
b10 '
#1250
b1 "
b11 '
#1300
b11 "
b100 '
#1350
b1 "
b101 '
#1400
b10 "
b110 '
#1450
b101 !
b1 "
b0 '
b0 %
b1 #
#1500
b110 !
b0 "
b1 '
#1550
b10 '
#1600
b11 '
#1650
b100 '
#1700
b101 '
#1750
b110 '
#1800
b101 !
b1 "
b0 '
b10011 %
#1850
b110 !
b11 "
b1 '
#1900
b0 "
b10 '
#1950
b11 "
b11 '
#2000
b1 "
b100 '
#2050
b11 "
b101 '
#2100
b0 "
b110 '
#2150
b101 !
b1 "
b0 '
b100110 %
#2200
b110 !
b10 "
b1 '
#2250
b1 "
b10 '
#2300
b10 "
b11 '
#2350
b100 '
#2400
b101 '
#2450
b1 "
b110 '
#2500
b101 !
b0 '
b111001 %
#2550
b110 !
b1 '
#2600
b10 "
b10 '
#2650
b1 "
b11 '
#2700
b11 "
b100 '
#2750
b1 "
b101 '
#2800
b10 "
b110 '
#2850
b101 !
b0 '
b0 %
b10 #
#2900
b110 !
b0 "
b1 '
#2950
b10 '
#3000
b11 '
#3050
b100 '
#3100
b101 '
#3150
b110 '
#3200
b101 !
b10 "
b0 '
b10011 %
#3250
b110 !
b11 "
b1 '
#3300
b0 "
b10 '
#3350
b11 "
b11 '
#3400
b1 "
b100 '
#3450
b11 "
b101 '
#3500
b0 "
b110 '
#3550
b101 !
b10 "
b0 '
b100110 %
#3600
b110 !
b1 '
#3650
b1 "
b10 '
#3700
b10 "
b11 '
#3750
b100 '
#3800
b101 '
#3850
b1 "
b110 '
#3900
b101 !
b10 "
b0 '
b111001 %
#3950
b110 !
b1 "
b1 '
#4000
b10 "
b10 '
#4050
b1 "
b11 '
#4100
b11 "
b100 '
#4150
b1 "
b101 '
#4200
b10 "
b110 '
b10 !
b0 (
b1 )
#4250
b1 !
b0 "
b0 '
b0 %
b0 #
#4300
b10 !
b1 '
#4350
b10 '
#4400
b11 '
#4450
b100 '
#4500
b101 '
#4550
b110 '
#4600
b1 !
b0 '
b10011 %
#4650
b10 !
b11 "
b1 '
#4700
b0 "
b10 '
#4750
b11 "
b11 '
#4800
b1 "
b100 '
#4850
b11 "
b101 '
#4900
b0 "
b110 '
#4950
b1 !
b0 '
b100110 %
#5000
b10 !
b10 "
b1 '
#5050
b1 "
b10 '
#5100
b10 "
b11 '
#5150
b100 '
#5200
b101 '
#5250
b1 "
b110 '
#5300
b1 !
b0 "
b0 '
b111001 %
#5350
b10 !
b1 "
b1 '
#5400
b10 "
b10 '
#5450
b1 "
b11 '
#5500
b11 "
b100 '
#5550
b1 "
b101 '
#5600
b10 "
b110 '
#5650
b1 !
b1 "
b0 '
b0 %
b1 #
#5700
b10 !
b0 "
b1 '
#5750
b10 '
#5800
b11 '
#5850
b100 '
#5900
b101 '
#5950
b110 '
#6000
b1 !
b1 "
b0 '
b10011 %
#6050
b10 !
b11 "
b1 '
#6100
b0 "
b10 '
#6150
b11 "
b11 '
#6200
b1 "
b100 '
#6250
b11 "
b101 '
#6300
b0 "
b110 '
#6350
b1 !
b1 "
b0 '
b100110 %
#6400
b10 !
b10 "
b1 '
#6450
b1 "
b10 '
#6500
b10 "
b11 '
#6550
b100 '
#6600
b101 '
#6650
b1 "
b110 '
#6700
b1 !
b0 '
b111001 %
#6750
b10 !
b1 '
#6800
b10 "
b10 '
#6850
b1 "
b11 '
#6900
b11 "
b100 '
#6950
b1 "
b101 '
#7000
b10 "
b110 '
#7050
b1 !
b0 '
b0 %
b10 #
#7100
b10 !
b0 "
b1 '
#7150
b10 '
#7200
b11 '
#7250
b100 '
#7300
b101 '
#7350
b110 '
#7400
b1 !
b10 "
b0 '
b10011 %
#7450
b10 !
b11 "
b1 '
#7500
b0 "
b10 '
#7550
b11 "
b11 '
#7600
b1 "
b100 '
#7650
b11 "
b101 '
#7700
b0 "
b110 '
#7750
b1 !
b10 "
b0 '
b100110 %
#7800
b10 !
b1 '
#7850
b1 "
b10 '
#7900
b10 "
b11 '
#7950
b100 '
#8000
b101 '
#8050
b1 "
b110 '
#8100
b1 !
b10 "
b0 '
b111001 %
#8150
b10 !
b1 "
b1 '
#8200
b10 "
b10 '
#8250
b1 "
b11 '
#8300
b11 "
b100 '
#8350
b1 "
b101 '
#8400
b10 "
b110 '
b100 !
b0 &
b100 (
b10 )
#8450
b101 !
b0 "
b0 '
b0 %
b0 #
#8500
b100 !
b1 '
#8550
b10 '
#8600
b11 '
#8650
b100 '
#8700
b101 '
#8750
b110 '
#8800
b101 !
b0 '
b10011 %
#8850
b100 !
b11 "
b1 '
#8900
b0 "
b10 '
#8950
b11 "
b11 '
#9000
b1 "
b100 '
#9050
b11 "
b101 '
#9100
b0 "
b110 '
#9150
b101 !
b0 '
b100110 %
#9200
b100 !
b10 "
b1 '
#9250
b1 "
b10 '
#9300
b10 "
b11 '
#9350
b100 '
#9400
b101 '
#9450
b1 "
b110 '
#9500
b101 !
b0 "
b0 '
b111001 %
#9550
b100 !
b1 "
b1 '
#9600
b10 "
b10 '
#9650
b1 "
b11 '
#9700
b11 "
b100 '
#9750
b1 "
b101 '
#9800
b10 "
b110 '
#9850
b101 !
b1 "
b0 '
b0 %
b1 #
#9900
b100 !
b0 "
b1 '
#9950
b10 '
#10000
b11 '
#10050
b100 '
#10100
b101 '
#10150
b110 '
#10200
b101 !
b1 "
b0 '
b10011 %
#10250
b100 !
b11 "
b1 '
#10300
b0 "
b10 '
#10350
b11 "
b11 '
#10400
b1 "
b100 '
#10450
b11 "
b101 '
#10500
b0 "
b110 '
#10550
b101 !
b1 "
b0 '
b100110 %
#10600
b100 !
b10 "
b1 '
#10650
b1 "
b10 '
#10700
b10 "
b11 '
#10750
b100 '
#10800
b101 '
#10850
b1 "
b110 '
#10900
b101 !
b0 '
b111001 %
#10950
b100 !
b1 '
#11000
b10 "
b10 '
#11050
b1 "
b11 '
#11100
b11 "
b100 '
#11150
b1 "
b101 '
#11200
b10 "
b110 '
#11250
b101 !
b0 '
b0 %
b10 #
#11300
b100 !
b0 "
b1 '
#11350
b10 '
#11400
b11 '
#11450
b100 '
#11500
b101 '
#11550
b110 '
#11600
b101 !
b10 "
b0 '
b10011 %
#11650
b100 !
b11 "
b1 '
#11700
b0 "
b10 '
#11750
b11 "
b11 '
#11800
b1 "
b100 '
#11850
b11 "
b101 '
#11900
b0 "
b110 '
#11950
b101 !
b10 "
b0 '
b100110 %
#12000
b100 !
b1 '
#12050
b1 "
b10 '
#12100
b10 "
b11 '
#12150
b100 '
#12200
b101 '
#12250
b1 "
b110 '
#12300
b101 !
b10 "
b0 '
b111001 %
#12350
b100 !
b1 "
b1 '
#12400
b10 "
b10 '
#12450
b1 "
b11 '
#12500
b11 "
b100 '
#12550
b1 "
b101 '
#12600
b10 "
b110 '
b10 !
b0 $
b10 &
b0 (
b11 )
#12650
b0 !
b0 "
b0 '
b0 %
b0 #
#12700
b10 !
b1 '
#12750
b10 '
#12800
b11 '
#12850
b100 '
#12900
b101 '
#12950
b110 '
#13000
b0 !
b0 '
b10011 %
#13050
b10 !
b11 "
b1 '
#13100
b0 "
b10 '
#13150
b11 "
b11 '
#13200
b1 "
b100 '
#13250
b11 "
b101 '
#13300
b0 "
b110 '
#13350
b0 !
b0 '
b100110 %
#13400
b10 !
b10 "
b1 '
#13450
b1 "
b10 '
#13500
b10 "
b11 '
#13550
b100 '
#13600
b101 '
#13650
b1 "
b110 '
#13700
b0 !
b0 "
b0 '
b111001 %
#13750
b10 !
b1 "
b1 '
#13800
b10 "
b10 '
#13850
b1 "
b11 '
#13900
b11 "
b100 '
#13950
b1 "
b101 '
#14000
b10 "
b110 '
#14050
b0 !
b1 "
b0 '
b0 %
b1 #
#14100
b10 !
b0 "
b1 '
#14150
b10 '
#14200
b11 '
#14250
b100 '
#14300
b101 '
#14350
b110 '
#14400
b0 !
b1 "
b0 '
b10011 %
#14450
b10 !
b11 "
b1 '
#14500
b0 "
b10 '
#14550
b11 "
b11 '
#14600
b1 "
b100 '
#14650
b11 "
b101 '
#14700
b0 "
b110 '
#14750
b0 !
b1 "
b0 '
b100110 %
#14800
b10 !
b10 "
b1 '
#14850
b1 "
b10 '
#14900
b10 "
b11 '
#14950
b100 '
#15000
b101 '
#15050
b1 "
b110 '
#15100
b0 !
b0 '
b111001 %
#15150
b10 !
b1 '
#15200
b10 "
b10 '
#15250
b1 "
b11 '
#15300
b11 "
b100 '
#15350
b1 "
b101 '
#15400
b10 "
b110 '
#15450
b0 !
b0 '
b0 %
b10 #
#15500
b10 !
b0 "
b1 '
#15550
b10 '
#15600
b11 '
#15650
b100 '
#15700
b101 '
#15750
b110 '
#15800
b0 !
b10 "
b0 '
b10011 %
#15850
b10 !
b11 "
b1 '
#15900
b0 "
b10 '
#15950
b11 "
b11 '
#16000
b1 "
b100 '
#16050
b11 "
b101 '
#16100
b0 "
b110 '
#16150
b0 !
b10 "
b0 '
b100110 %
#16200
b10 !
b1 '
#16250
b1 "
b10 '
#16300
b10 "
b11 '
#16350
b100 '
#16400
b101 '
#16450
b1 "
b110 '
#16500
b0 !
b10 "
b0 '
b111001 %
#16550
b10 !
b1 "
b1 '
#16600
b10 "
b10 '
#16650
b1 "
b11 '
#16700
b11 "
b100 '
#16750
b1 "
b101 '
#16800
b10 "
b110 '
b1 $
b100 )
#16850
b1 !
b0 "
b0 '
b0 %
b0 #
#16900
b10 !
b1 '
#16950
b10 '
#17000
b11 '
#17050
b100 '
#17100
b101 '
#17150
b110 '
#17200
b1 !
b0 '
b10011 %
#17250
b10 !
b11 "
b1 '
#17300
b0 "
b10 '
#17350
b11 "
b11 '
#17400
b1 "
b100 '
#17450
b11 "
b101 '
#17500
b0 "
b110 '
#17550
b1 !
b0 '
b100110 %
#17600
b10 !
b10 "
b1 '
#17650
b1 "
b10 '
#17700
b10 "
b11 '
#17750
b100 '
#17800
b101 '
#17850
b1 "
b110 '
#17900
b1 !
b0 "
b0 '
b111001 %
#17950
b10 !
b1 "
b1 '
#18000
b10 "
b10 '
#18050
b1 "
b11 '
#18100
b11 "
b100 '
#18150
b1 "
b101 '
#18200
b10 "
b110 '
#18250
b1 !
b1 "
b0 '
b0 %
b1 #
#18300
b10 !
b0 "
b1 '
#18350
b10 '
#18400
b11 '
#18450
b100 '
#18500
b101 '
#18550
b110 '
#18600
b1 !
b1 "
b0 '
b10011 %
#18650
b10 !
b11 "
b1 '
#18700
b0 "
b10 '
#18750
b11 "
b11 '
#18800
b1 "
b100 '
#18850
b11 "
b101 '
#18900
b0 "
b110 '
#18950
b1 !
b1 "
b0 '
b100110 %
#19000
b10 !
b10 "
b1 '
#19050
b1 "
b10 '
#19100
b10 "
b11 '
#19150
b100 '
#19200
b101 '
#19250
b1 "
b110 '
#19300
b1 !
b0 '
b111001 %
#19350
b10 !
b1 '
#19400
b10 "
b10 '
#19450
b1 "
b11 '
#19500
b11 "
b100 '
#19550
b1 "
b101 '
#19600
b10 "
b110 '
#19650
b1 !
b0 '
b0 %
b10 #
#19700
b10 !
b0 "
b1 '
#19750
b10 '
#19800
b11 '
#19850
b100 '
#19900
b101 '
#19950
b110 '
#20000
b1 !
b10 "
b0 '
b10011 %
#20050
b10 !
b11 "
b1 '
#20100
b0 "
b10 '
#20150
b11 "
b11 '
#20200
b1 "
b100 '
#20250
b11 "
b101 '
#20300
b0 "
b110 '
#20350
b1 !
b10 "
b0 '
b100110 %
#20400
b10 !
b1 '
#20450
b1 "
b10 '
#20500
b10 "
b11 '
#20550
b100 '
#20600
b101 '
#20650
b1 "
b110 '
#20700
b1 !
b10 "
b0 '
b111001 %
#20750
b10 !
b1 "
b1 '
#20800
b10 "
b10 '
#20850
b1 "
b11 '
#20900
b11 "
b100 '
#20950
b1 "
b101 '
#21000
b10 "
b110 '
b100 !
b0 $
b0 &
b100 (
b101 )
#21050
b0 "
b0 '
b0 %
b0 #
#21100
b1 '
#21150
b10 '
#21200
b11 '
#21250
b100 '
#21300
b101 '
#21350
b110 '
#21400
b0 '
b10011 %
#21450
b11 "
b1 '
#21500
b0 "
b10 '
#21550
b11 "
b11 '
#21600
b1 "
b100 '
#21650
b11 "
b101 '
#21700
b0 "
b110 '
#21750
b0 '
b100110 %
#21800
b10 "
b1 '
#21850
b1 "
b10 '
#21900
b10 "
b11 '
#21950
b100 '
#22000
b101 '
#22050
b1 "
b110 '
#22100
b0 "
b0 '
b111001 %
#22150
b1 "
b1 '
#22200
b10 "
b10 '
#22250
b1 "
b11 '
#22300
b11 "
b100 '
#22350
b1 "
b101 '
#22400
b10 "
b110 '
#22450
b1 "
b0 '
b0 %
b1 #
#22500
b0 "
b1 '
#22550
b10 '
#22600
b11 '
#22650
b100 '
#22700
b101 '
#22750
b110 '
#22800
b1 "
b0 '
b10011 %
#22850
b11 "
b1 '
#22900
b0 "
b10 '
#22950
b11 "
b11 '
#23000
b1 "
b100 '
#23050
b11 "
b101 '
#23100
b0 "
b110 '
#23150
b1 "
b0 '
b100110 %
#23200
b10 "
b1 '
#23250
b1 "
b10 '
#23300
b10 "
b11 '
#23350
b100 '
#23400
b101 '
#23450
b1 "
b110 '
#23500
b0 '
b111001 %
#23550
b1 '
#23600
b10 "
b10 '
#23650
b1 "
b11 '
#23700
b11 "
b100 '
#23750
b1 "
b101 '
#23800
b10 "
b110 '
#23850
b0 '
b0 %
b10 #
#23900
b0 "
b1 '
#23950
b10 '
#24000
b11 '
#24050
b100 '
#24100
b101 '
#24150
b110 '
#24200
b10 "
b0 '
b10011 %
#24250
b11 "
b1 '
#24300
b0 "
b10 '
#24350
b11 "
b11 '
#24400
b1 "
b100 '
#24450
b11 "
b101 '
#24500
b0 "
b110 '
#24550
b10 "
b0 '
b100110 %
#24600
b1 '
#24650
b1 "
b10 '
#24700
b10 "
b11 '
#24750
b100 '
#24800
b101 '
#24850
b1 "
b110 '
#24900
b10 "
b0 '
b111001 %
#24950
b1 "
b1 '
#25000
b10 "
b10 '
#25050
b1 "
b11 '
#25100
b11 "
b100 '
#25150
b1 "
b101 '
#25200
b10 "
b110 '
b110 !
b10 &
b110 )
#25250
b100 !
b0 "
b0 '
b0 %
b0 #
#25300
b110 !
b1 '
#25350
b10 '
#25400
b11 '
#25450
b100 '
#25500
b101 '
#25550
b110 '
#25600
b100 !
b0 '
b10011 %
#25650
b110 !
b11 "
b1 '
#25700
b0 "
b10 '
#25750
b11 "
b11 '
#25800
b1 "
b100 '
#25850
b11 "
b101 '
#25900
b0 "
b110 '
#25950
b100 !
b0 '
b100110 %
#26000
b110 !
b10 "
b1 '
#26050
b1 "
b10 '
#26100
b10 "
b11 '
#26150
b100 '
#26200
b101 '
#26250
b1 "
b110 '
#26300
b100 !
b0 "
b0 '
b111001 %
#26350
b110 !
b1 "
b1 '
#26400
b10 "
b10 '
#26450
b1 "
b11 '
#26500
b11 "
b100 '
#26550
b1 "
b101 '
#26600
b10 "
b110 '
#26650
b100 !
b1 "
b0 '
b0 %
b1 #
#26700
b110 !
b0 "
b1 '
#26750
b10 '
#26800
b11 '
#26850
b100 '
#26900
b101 '
#26950
b110 '
#27000
b100 !
b1 "
b0 '
b10011 %
#27050
b110 !
b11 "
b1 '
#27100
b0 "
b10 '
#27150
b11 "
b11 '
#27200
b1 "
b100 '
#27250
b11 "
b101 '
#27300
b0 "
b110 '
#27350
b100 !
b1 "
b0 '
b100110 %
#27400
b110 !
b10 "
b1 '
#27450
b1 "
b10 '
#27500
b10 "
b11 '
#27550
b100 '
#27600
b101 '
#27650
b1 "
b110 '
#27700
b100 !
b0 '
b111001 %
#27750
b110 !
b1 '
#27800
b10 "
b10 '
#27850
b1 "
b11 '
#27900
b11 "
b100 '
#27950
b1 "
b101 '
#28000
b10 "
b110 '
#28050
b100 !
b0 '
b0 %
b10 #
#28100
b110 !
b0 "
b1 '
#28150
b10 '
#28200
b11 '
#28250
b100 '
#28300
b101 '
#28350
b110 '
#28400
b100 !
b10 "
b0 '
b10011 %
#28450
b110 !
b11 "
b1 '
#28500
b0 "
b10 '
#28550
b11 "
b11 '
#28600
b1 "
b100 '
#28650
b11 "
b101 '
#28700
b0 "
b110 '
#28750
b100 !
b10 "
b0 '
b100110 %
#28800
b110 !
b1 '
#28850
b1 "
b10 '
#28900
b10 "
b11 '
#28950
b100 '
#29000
b101 '
#29050
b1 "
b110 '
#29100
b100 !
b10 "
b0 '
b111001 %
#29150
b110 !
b1 "
b1 '
#29200
b10 "
b10 '
#29250
b1 "
b11 '
#29300
b11 "
b100 '
#29350
b1 "
b101 '
#29400
b10 "
b110 '
b100 !
b1 $
b0 &
b111 )
#29450
b101 !
b0 "
b0 '
b0 %
b0 #
#29500
b100 !
b1 '
#29550
b10 '
#29600
b11 '
#29650
b100 '
#29700
b101 '
#29750
b110 '
#29800
b101 !
b0 '
b10011 %
#29850
b100 !
b11 "
b1 '
#29900
b0 "
b10 '
#29950
b11 "
b11 '
#30000
b1 "
b100 '
#30050
b11 "
b101 '
#30100
b0 "
b110 '
#30150
b101 !
b0 '
b100110 %
#30200
b100 !
b10 "
b1 '
#30250
b1 "
b10 '
#30300
b10 "
b11 '
#30350
b100 '
#30400
b101 '
#30450
b1 "
b110 '
#30500
b101 !
b0 "
b0 '
b111001 %
#30550
b100 !
b1 "
b1 '
#30600
b10 "
b10 '
#30650
b1 "
b11 '
#30700
b11 "
b100 '
#30750
b1 "
b101 '
#30800
b10 "
b110 '
#30850
b101 !
b1 "
b0 '
b0 %
b1 #
#30900
b100 !
b0 "
b1 '
#30950
b10 '
#31000
b11 '
#31050
b100 '
#31100
b101 '
#31150
b110 '
#31200
b101 !
b1 "
b0 '
b10011 %
#31250
b100 !
b11 "
b1 '
#31300
b0 "
b10 '
#31350
b11 "
b11 '
#31400
b1 "
b100 '
#31450
b11 "
b101 '
#31500
b0 "
b110 '
#31550
b101 !
b1 "
b0 '
b100110 %
#31600
b100 !
b10 "
b1 '
#31650
b1 "
b10 '
#31700
b10 "
b11 '
#31750
b100 '
#31800
b101 '
#31850
b1 "
b110 '
#31900
b101 !
b0 '
b111001 %
#31950
b100 !
b1 '
#32000
b10 "
b10 '
#32050
b1 "
b11 '
#32100
b11 "
b100 '
#32150
b1 "
b101 '
#32200
b10 "
b110 '
#32250
b101 !
b0 '
b0 %
b10 #
#32300
b100 !
b0 "
b1 '
#32350
b10 '
#32400
b11 '
#32450
b100 '
#32500
b101 '
#32550
b110 '
#32600
b101 !
b10 "
b0 '
b10011 %
#32650
b100 !
b11 "
b1 '
#32700
b0 "
b10 '
#32750
b11 "
b11 '
#32800
b1 "
b100 '
#32850
b11 "
b101 '
#32900
b0 "
b110 '
#32950
b101 !
b10 "
b0 '
b100110 %
#33000
b100 !
b1 '
#33050
b1 "
b10 '
#33100
b10 "
b11 '
#33150
b100 '
#33200
b101 '
#33250
b1 "
b110 '
#33300
b101 !
b10 "
b0 '
b111001 %
#33350
b100 !
b1 "
b1 '
#33400
b10 "
b10 '
#33450
b1 "
b11 '
#33500
b11 "
b100 '
#33550
b1 "
b101 '
#33600
b10 "
b110 '
b1000 )
