tests/testfiles/SPI_Slave/SPI_Slave.v
module SPI_Slave
(
reset,
In_Data,
slaveCPOL, 
slaveCPHA,
slaveSCLK, 
slaveCS_, 
slaveMISO, 
slaveMOSI,
slave_start,
read_data
);                   //SCLK: SPI clock; //MOSI: Master out Slave in;  
                                //MISO: Master in Slave out; //ExData: External data to be communicated
input wire [7:0] In_Data;
input wire reset;
input wire slaveSCLK, slaveCPOL, slaveCPHA; 
input wire slaveCS_;
input wire slaveMOSI; 
input wire slave_start;

output reg slaveMISO;
output wire [7:0] read_data; // output_data, the data from Master

reg [7:0] memReg;//internal memory register


always@ (posedge reset)
begin
memReg = In_Data;
end

always@(negedge slaveCS_)
 slaveMISO = memReg[0]; //sending
    
always @ (negedge slaveSCLK) 
begin
if(slaveCS_==0)
begin
    if(slave_start==1)
    begin
     if ({slaveCPOL,slaveCPHA}==0 ||{slaveCPOL,slaveCPHA}==2 ) // send on falling 
     slaveMISO = memReg[0]; //sending
     
     if ({slaveCPOL,slaveCPHA}==1 ||{slaveCPOL,slaveCPHA}==3 ) // read on falling
     memReg ={slaveMOSI,memReg[7:1]};

    end
  
 end
end
always@(posedge slaveSCLK) // rising edge
begin
if(slaveCS_==0)
begin

 if(slave_start==1)
begin
    if ({slaveCPOL,slaveCPHA}==1 ||{slaveCPOL,slaveCPHA}==3 ) // send on rising
    slaveMISO = memReg[0];
    if ({slaveCPOL,slaveCPHA}==0 ||{slaveCPOL,slaveCPHA}==2 ) // read on rising
    memReg <={slaveMOSI,memReg[7:1]};
end
end
end
assign read_data = memReg;

endmodule

tests/testfiles/SPI_Slave/SPI_Slave_tb.v
`timescale 1 ns/ 10 ps 	

module SPI_Slave_tb();

localparam PERIOD = 4;
reg [7:0] In_Data;
reg reset;
reg slaveCPOL,slaveCPHA;
reg slaveSCLK;
reg slaveCS_;
reg slave_start;
reg slaveMOSI;
wire slaveMISO;
wire [7:0] read_data;
reg [7:0] Master_Memory; //write memory
integer i;
reg [7:0] MOSI_Arr;

SPI_Slave Slave
(
 .reset(reset),
 .slaveSCLK(slaveSCLK),
 .slaveCPOL(slaveCPOL),
 .slaveCPHA(slaveCPHA),
 .slaveMISO(slaveMISO),
 .slaveMOSI(slaveMOSI),
 .slaveCS_(slaveCS_),
 .In_Data(In_Data),
 .read_data(read_data),
 .slave_start(slave_start)
);

always 
   #(PERIOD/2) slaveSCLK = ~slaveSCLK;


initial
begin
$monitor ("%g\t %b\t %b\t %b\t %b\t %b\t %b\t          %b\t    %b\t    %b\t  %b\t",
           $time, reset,slaveCPOL,slaveCPHA,slaveSCLK,slaveCS_,slave_start,read_data,slaveMOSI,slaveMISO,Master_Memory);


//mode 0
{slaveCPOL,slaveCPHA}=0; slaveSCLK = slaveCPOL;  In_Data = 8'b00001111;  reset = 1'b1; MOSI_Arr = 8'b10101010; slaveCS_ = 1'b1;
$display("#################################################_______MODE_0___####################################################################################################");
$display ("time\t reset\t slaveCPOL\t slaveCPHA\t slaveSCLK\t slaveCS_\tSlave_Start\t   read_data\t slaveMOSI\t slaveMISO\t Write_Memory");


#(PERIOD)  slaveCS_ = 1'b0;  reset = 1'b0;
for(i=0;i<8;i=i+1)
begin
  #(PERIOD/2) // +ve sclk, reading from slaveMOSI and writing the first bit on slaveMISO
  slaveMOSI = MOSI_Arr[i]; slave_start = 1;
  #(PERIOD/2) // -ve sclk , writing bits starting from 2nd bit on slaveMISO
  Master_Memory[i]=slaveMISO;
end

#(PERIOD/2)

  if(Master_Memory==In_Data && read_data==MOSI_Arr)
    $display("Data was transmitted successfully");
    else
begin
     for(i=0;i<8;i=i+1)
     begin
     if(Master_Memory[i]!=In_Data[i])
     $display("Error in write memory in index %d, expected %b, found %b",i,In_Data[i],Master_Memory[i]);
     end
     for(i=0;i<8;i=i+1)
     begin
     if(read_data[i]!=MOSI_Arr[i])
     $display("Error in slave memory in index %d, expected %b, found %b",i,In_Data[i],Master_Memory[i]);
     end
end


  //Mode 1
{slaveCPOL,slaveCPHA} = 1; slaveSCLK = slaveCPOL;  In_Data = 8'b11011000;  reset = 1'b1;
 MOSI_Arr = 8'b01110110; slaveCS_ = 1'b1; Master_Memory = 8'bx; slave_start=0;

$display("#################################################_______MODE_1______###########################################################################");
$display ("time\t reset\t slaveCPOL\t slaveCPHA\t slaveSCLK\t slaveCS_\tSlave_Start\t   read_data\t slaveMOSI\t slaveMISO\t Write_Memory");

for(i=0;i<8;i=i+1)
begin
  #(PERIOD/2)
slave_start = 1;
  slaveCS_ = 1'b0;  reset = 1'b0; 
 //+ve sclk
  #(PERIOD/2) // -ve sclk

  slaveMOSI = MOSI_Arr[i];
   Master_Memory[i] = slaveMISO;
 
 end
#(PERIOD)
  if(Master_Memory==In_Data && read_data==MOSI_Arr)
    $display("Data was transmitted successfully");
    else
      begin
     for(i=0;i<8;i=i+1)
     begin
     if(Master_Memory[i]!=In_Data[i])
     $display("Error in write memory in index %d, expected %b, found %b",i,In_Data[i],Master_Memory[i]);
     end
     for(i=0;i<8;i=i+1)
     begin
     if(read_data[i]!=MOSI_Arr[i])
     $display("Error in slave memory in index %d, expected %b, found %b",i,In_Data[i],Master_Memory[i]);
     end
end


//Mode2
{slaveCPOL,slaveCPHA} = 2; slaveSCLK = slaveCPOL;  In_Data = 8'b01011001;  reset = 1'b1; 
 MOSI_Arr = 8'b00000000; slaveCS_ = 1'b1; Master_Memory = 8'bx; slave_start=0;
$display("#################################################_______MODE_2______############################################################################");
$display ("time\t reset\t slaveCPOL\t slaveCPHA\t slaveSCLK\t slaveCS_\tSlave_Start\t   read_data\t slaveMOSI\t slaveMISO\t Write_Memory");


for(i=0;i<8;i=i+1)
begin
  #(PERIOD/2)
  slaveCS_ = 1'b0; reset = 1'b0;
   slaveMOSI = MOSI_Arr[i]; slave_start = 1;
  #(PERIOD/2)
  Master_Memory[i] = slaveMISO;
end
#(PERIOD)

  if(Master_Memory==In_Data && read_data==MOSI_Arr)
    $display("Data was transmitted successfully");
    else
     begin
     for(i=0;i<8;i=i+1)
     begin
     if(Master_Memory[i]!=In_Data[i])
     $display("Error in write memory in index %d, expected %b, found %b",i,In_Data[i],Master_Memory[i]);
     end
     for(i=0;i<8;i=i+1)
     begin
     if(read_data[i]!=MOSI_Arr[i])
     $display("Error in slave memory in index %d, expected %b, found %b",i,In_Data[i],Master_Memory[i]);
     end
     end

//Mode 3
{slaveCPOL,slaveCPHA} = 3; slaveSCLK = slaveCPOL;  In_Data = 8'b00011011;  reset = 1'b1;
 MOSI_Arr = 8'b11111111; slaveCS_ = 1'b1; Master_Memory = 8'bx; slave_start=0;
$display("#################################################_______MODE_3_______############################################################################");
$display ("time\t reset\t slaveCPOL\t slaveCPHA\t slaveSCLK\t slaveCS_\tSlave_Start\t   read_data\t slaveMOSI\t slaveMISO\t Write_Memory");


for(i=0;i<8;i=i+1)
begin
  #(PERIOD/2)
  slaveCS_ = 1'b0; reset = 1'b0; 
  slave_start = 1;
  #(PERIOD/2)
  slaveMOSI = MOSI_Arr[i];
  Master_Memory[i] = slaveMISO;
end
  #(PERIOD)
  if(Master_Memory==In_Data && read_data==MOSI_Arr)
    $display("Data was transmitted successfully");
    else
     begin
     for(i=0;i<8;i=i+1)
     begin
     if(Master_Memory[i]!=In_Data[i])
     $display("Error in write memory in index %d, expected %b, found %b",i,In_Data[i],Master_Memory[i]);
     end
     for(i=0;i<8;i=i+1)
     begin
     if(read_data[i]!=MOSI_Arr[i])
     $display("Error in slave memory in index %d, expected %b, found %b",i,In_Data[i],Master_Memory[i]);
     end
end



$finish;
end

initial
	begin
		$dumpfile(`DUMP_FILE_NAME);
        //$dumpfile("SPI_Master.vcd");
		$dumpvars();		//writing the vcd file
	end

endmodule

tests/testfiles/SPI_Slave/SPI_Slave.vcd
$date
	Fri Mar 15 07:08:31 2024
$end
$version
	Icarus Verilog
$end
$timescale
	10ps
$end
$scope module SPI_Slave_tb $end
$var wire 1 ! slaveMISO $end
$var wire 8 " read_data [7:0] $end
$var parameter 32 # PERIOD $end
$var reg 8 $ In_Data [7:0] $end
$var reg 8 % MOSI_Arr [7:0] $end
$var reg 8 & Master_Memory [7:0] $end
$var reg 1 ' reset $end
$var reg 1 ( slaveCPHA $end
$var reg 1 ) slaveCPOL $end
$var reg 1 * slaveCS_ $end
$var reg 1 + slaveMOSI $end
$var reg 1 , slaveSCLK $end
$var reg 1 - slave_start $end
$var integer 32 . i [31:0] $end
$scope module Slave $end
$var wire 8 / In_Data [7:0] $end
$var wire 8 0 read_data [7:0] $end
$var wire 1 ' reset $end
$var wire 1 ( slaveCPHA $end
$var wire 1 ) slaveCPOL $end
$var wire 1 * slaveCS_ $end
$var wire 1 + slaveMOSI $end
$var wire 1 , slaveSCLK $end
$var wire 1 - slave_start $end
$var reg 8 1 memReg [7:0] $end
$var reg 1 ! slaveMISO $end
$upscope $end
$upscope $end
$enddefinitions $end
$comment Show the parameter values. $end
$dumpall
b100 #
$end
#0
$dumpvars
b1111 1
b1111 0
b1111 /
bx .
x-
0,
x+
1*
0)
0(
1'
bx &
b10101010 %
b1111 $
b1111 "
x!
$end
#200
1,
#400
1!
0,
b0 .
0'
0*
#600
b111 "
b111 0
b111 1
1,
1-
0+
#800
0,
b1 .
bx1 &
#1000
b10000011 "
b10000011 0
b10000011 1
1,
1+
#1200
0,
b10 .
bx11 &
#1400
b1000001 "
b1000001 0
b1000001 1
1,
0+
#1600
0,
b11 .
bx111 &
#1800
b10100000 "
b10100000 0
b10100000 1
1,
1+
#2000
0!
0,
b100 .
bx1111 &
#2200
b1010000 "
b1010000 0
b1010000 1
1,
0+
#2400
0,
b101 .
bx01111 &
#2600
b10101000 "
b10101000 0
b10101000 1
1,
1+
#2800
0,
b110 .
bx001111 &
#3000
b1010100 "
b1010100 0
b1010100 1
1,
0+
#3200
0,
b111 .
bx0001111 &
#3400
b10101010 "
b10101010 0
b10101010 1
1,
1+
#3600
0,
b1000 .
b1111 &
#3800
b11011000 "
b11011000 0
b11011000 1
1,
b0 .
0-
bx &
1*
b1110110 %
1'
b11011000 $
b11011000 /
1(
#4000
b11101100 "
b11101100 0
b11101100 1
0,
0'
0*
1-
#4200
1,
b1 .
bx0 &
0+
#4400
b1110110 "
b1110110 0
b1110110 1
0,
#4600
1,
b10 .
bx00 &
1+
#4800
b10111011 "
b10111011 0
b10111011 1
0,
#5000
1!
1,
b11 .
bx000 &
#5200
b11011101 "
b11011101 0
b11011101 1
0,
#5400
1,
b100 .
bx1000 &
0+
#5600
b1101110 "
b1101110 0
b1101110 1
0,
#5800
0!
1,
b101 .
bx11000 &
1+
#6000
b10110111 "
b10110111 0
b10110111 1
0,
#6200
1!
1,
b110 .
bx011000 &
#6400
b11011011 "
b11011011 0
b11011011 1
0,
#6600
1,
b111 .
bx1011000 &
#6800
b11101101 "
b11101101 0
b11101101 1
0,
#7000
1,
b1000 .
b11011000 &
0+
#7200
b1110110 "
b1110110 0
b1110110 1
0,
#7400
b1011001 "
b1011001 0
b1011001 1
b0 .
0-
bx &
1*
b0 %
1'
b1011001 $
b1011001 /
0,
1)
0(
#7600
b101100 "
b101100 0
b101100 1
1,
1-
0'
0*
#7800
0!
0,
b1 .
bx1 &
#8000
b10110 "
b10110 0
b10110 1
1,
#8200
0,
b10 .
bx01 &
#8400
b1011 "
b1011 0
b1011 1
1,
#8600
1!
0,
b11 .
bx001 &
#8800
b101 "
b101 0
b101 1
1,
#9000
0,
b100 .
bx1001 &
#9200
b10 "
b10 0
b10 1
1,
#9400
0!
0,
b101 .
bx11001 &
#9600
b1 "
b1 0
b1 1
1,
#9800
1!
0,
b110 .
bx011001 &
#10000
b0 "
b0 0
b0 1
1,
#10200
0!
0,
b111 .
bx1011001 &
#10400
1,
#10600
0,
b1000 .
b1011001 &
#10800
1,
#11000
b11011 "
b11011 0
b11011 1
0,
b0 .
0-
bx &
1*
b11111111 %
1'
b11011 $
b11011 /
1(
#11200
1!
1,
1-
0'
0*
#11400
b10001101 "
b10001101 0
b10001101 1
0,
b1 .
bx1 &
1+
#11600
1,
#11800
b11000110 "
b11000110 0
b11000110 1
0,
b10 .
bx11 &
#12000
0!
1,
#12200
b11100011 "
b11100011 0
b11100011 1
0,
b11 .
bx011 &
#12400
1!
1,
#12600
b11110001 "
b11110001 0
b11110001 1
0,
b100 .
bx1011 &
#12800
1,
#13000
b11111000 "
b11111000 0
b11111000 1
0,
b101 .
bx11011 &
#13200
0!
1,
#13400
b11111100 "
b11111100 0
b11111100 1
0,
b110 .
bx011011 &
#13600
1,
#13800
b11111110 "
b11111110 0
b11111110 1
0,
b111 .
bx0011011 &
#14000
1,
#14200
b11111111 "
b11111111 0
b11111111 1
0,
b1000 .
b11011 &
#14400
1!
1,
