tests/testfiles/ift/flipFlops/adffe/adffe_ift.v
module m_0 (ARST, ARST_t, CLK, CLK_t, D, D_t, EN, EN_t, Q, Q_t);

parameter WIDTH = 2;
parameter CLK_POLARITY = 1'b1;
parameter EN_POLARITY = 1'b1;
parameter ARST_POLARITY = 1'b1;
parameter ARST_VALUE = 2;

input CLK, ARST, EN;
input [WIDTH-1:0] D;
input [31:0] CLK_t;
input [31:0] ARST_t;
input [31:0] D_t;
input [31:0] EN_t;
output reg [WIDTH-1:0] Q;
output reg [31:0] Q_t;
wire pos_clk = CLK == CLK_POLARITY;
wire pos_arst = ARST == ARST_POLARITY;

initial begin
    Q_t = 0;
end

always @(posedge pos_clk, posedge pos_arst) begin
	if (pos_arst)begin
		Q <= ARST_VALUE;
		Q_t <= (^D === 1'bx) ? 0 : ((D == ARST_VALUE) ? (D_t | ARST_t) : ARST_t);
		end
	else if (EN == EN_POLARITY)begin
		Q <= D;
		Q_t <= (^D === 1'bx) ? 0 : (((D == ARST_VALUE) ? (D_t | ARST_t) : D_t) | EN_t);
		end
end



endmodule

tests/testfiles/ift/flipFlops/adffe/adffe_ift_tb.v
`timescale 1ns/1ps
module adffe_tb();
	reg [1:0] D;
	reg CLK;
	wire[1:0] Q;
	reg ARST;
	reg EN;
	
	reg [31:0] D_t;
	reg [31:0] CLK_t = 0;
	reg [31:0] ARST_t;
	reg [31:0] EN_t;
	wire [31:0] Q_t;
	
	reg[95:0] read_data [0:7];
	integer i;

	m_0 d1(ARST, ARST_t, CLK, CLK_t, D, D_t, EN, EN_t, Q, Q_t);

	initial begin
  		CLK=0;
     		forever #10 CLK = ~CLK;  
	end 

	initial begin 
	$readmemb(`INPUT_FILE_NAME, read_data);
		for(i = 0; i<8; i+=1) begin
		{ARST_t, D_t, EN_t} = read_data[i];
		 #5;
		 EN <= 1;
		 #40;
		 D <= 'b00;
		 #5;
		 ARST <= 1;
		 #5;
		 ARST <= 0;
		 #40;
		 D <= 'b01;
		 #5;
		 ARST <= 1;
		 #5;
		 ARST <= 0;
		 #40;
		 D <= 'b10;
		 #5;
		 ARST <= 1;
		 #5;
		 ARST <= 0;
		 #40;
		 D <= 'b11;
		 #5;
		 ARST <= 1;
		 #5;
		 ARST <= 0;
		 #40;
		  
		 #5;
		 EN <= 0;
		 #40;
		 D <= 'b00;
		 #5;
		 ARST <= 1;
		 #5;
		 ARST <= 0;
		 #40;
		 D <= 'b01;
		 #5;
		 ARST <= 1;
		 #5;
		 ARST <= 0;
		 #40;
		 D <= 'b10;
		 #5;
		 ARST <= 1;
		 #5;
		 ARST <= 0;
		 #40;
		 D <= 'b11;
		 #5;
		 ARST <= 1;
		 #5;
		 ARST <= 0;
		 #40;
		 end
		 
		 $finish;
	end
	initial
	begin
		$dumpfile(`DUMP_FILE_NAME);
		$dumpvars(1);		//writing the vcd file
	end
 	
endmodule

tests/testfiles/ift/flipFlops/adffe/adffe_ift.vcd
$date
	Mon Feb  5 16:42:00 2024
$end
$version
	Icarus Verilog
$end
$timescale
	1ps
$end
$scope module adffe_tb $end
$var wire 32 ! Q_t [31:0] $end
$var wire 2 " Q [1:0] $end
$var reg 1 # ARST $end
$var reg 32 $ ARST_t [31:0] $end
$var reg 1 % CLK $end
$var reg 32 & CLK_t [31:0] $end
$var reg 2 ' D [1:0] $end
$var reg 32 ( D_t [31:0] $end
$var reg 1 ) EN $end
$var reg 32 * EN_t [31:0] $end
$var integer 32 + i [31:0] $end
$upscope $end
$enddefinitions $end
$comment Show the parameter values. $end
$dumpall
$end
#0
$dumpvars
b0 +
b100 *
x)
b10 (
bx '
b0 &
0%
b1 $
x#
bx "
b0 !
$end
#5000
1)
#10000
1%
#20000
0%
#30000
1%
#40000
0%
#45000
b0 '
#50000
b1 !
b10 "
1#
1%
#55000
0#
#60000
0%
#70000
b110 !
b0 "
1%
#80000
0%
#90000
1%
#95000
b1 '
#100000
b1 !
b10 "
1#
0%
#105000
0#
#110000
b110 !
b1 "
1%
#120000
0%
#130000
1%
#140000
0%
#145000
b10 '
#150000
b11 !
b10 "
1#
1%
#155000
0#
#160000
0%
#170000
b111 !
1%
#180000
0%
#190000
1%
#195000
b11 '
#200000
b1 !
1#
0%
#205000
0#
#210000
b110 !
b11 "
1%
#220000
0%
#230000
1%
#240000
0%
#250000
0)
1%
#260000
0%
#270000
1%
#280000
0%
#290000
b0 '
1%
#295000
b1 !
b10 "
1#
#300000
0#
0%
#310000
1%
#320000
0%
#330000
1%
#340000
b1 '
0%
#345000
1#
#350000
0#
1%
#360000
0%
#370000
1%
#380000
0%
#390000
b10 '
1%
#395000
b11 !
1#
#400000
0#
0%
#410000
1%
#420000
0%
#430000
1%
#440000
b11 '
0%
#445000
b1 !
1#
#450000
0#
1%
#460000
0%
#470000
1%
#480000
0%
#490000
1%
b0 *
b1 +
#495000
1)
#500000
0%
#510000
b10 !
b11 "
1%
#520000
0%
#530000
1%
#535000
b0 '
#540000
b1 !
b10 "
1#
0%
#545000
0#
#550000
b10 !
b0 "
1%
#560000
0%
#570000
1%
#580000
0%
#585000
b1 '
#590000
b1 !
b10 "
1#
1%
#595000
0#
#600000
0%
#610000
b10 !
b1 "
1%
#620000
0%
#630000
1%
#635000
b10 '
#640000
b11 !
b10 "
1#
0%
#645000
0#
#650000
1%
#660000
0%
#670000
1%
#680000
0%
#685000
b11 '
#690000
b1 !
b10 "
1#
1%
#695000
0#
#700000
0%
#710000
b10 !
b11 "
1%
#720000
0%
#730000
1%
#740000
0)
0%
#750000
1%
#760000
0%
#770000
1%
#780000
b0 '
0%
#785000
b1 !
b10 "
1#
#790000
0#
1%
#800000
0%
#810000
1%
#820000
0%
#830000
b1 '
1%
#835000
1#
#840000
0#
0%
#850000
1%
#860000
0%
#870000
1%
#880000
b10 '
0%
#885000
b11 !
1#
#890000
0#
1%
#900000
0%
#910000
1%
#920000
0%
#930000
b11 '
1%
#935000
b1 !
1#
#940000
0#
0%
#950000
1%
#960000
0%
#970000
1%
#980000
0%
b0 (
b100 *
b10 +
#985000
1)
#990000
b100 !
b11 "
1%
#1000000
0%
#1010000
1%
#1020000
0%
#1025000
b0 '
#1030000
b1 !
b10 "
1#
1%
#1035000
0#
#1040000
0%
#1050000
b100 !
b0 "
1%
#1060000
0%
#1070000
1%
#1075000
b1 '
#1080000
b1 !
b10 "
1#
0%
#1085000
0#
#1090000
b100 !
b1 "
1%
#1100000
0%
#1110000
1%
#1120000
0%
#1125000
b10 '
#1130000
b1 !
b10 "
1#
1%
#1135000
0#
#1140000
0%
#1150000
b101 !
1%
#1160000
0%
#1170000
1%
#1175000
b11 '
#1180000
b1 !
1#
0%
#1185000
0#
#1190000
b100 !
b11 "
1%
#1200000
0%
#1210000
1%
#1220000
0%
#1230000
0)
1%
#1240000
0%
#1250000
1%
#1260000
0%
#1270000
b0 '
1%
#1275000
b1 !
b10 "
1#
#1280000
0#
0%
#1290000
1%
#1300000
0%
#1310000
1%
#1320000
b1 '
0%
#1325000
1#
#1330000
0#
1%
#1340000
0%
#1350000
1%
#1360000
0%
#1370000
b10 '
1%
#1375000
1#
#1380000
0#
0%
#1390000
1%
#1400000
0%
#1410000
1%
#1420000
b11 '
0%
#1425000
1#
#1430000
0#
1%
#1440000
0%
#1450000
1%
#1460000
0%
#1470000
1%
b0 $
b10 (
b0 *
b11 +
#1475000
1)
#1480000
0%
#1490000
b10 !
b11 "
1%
#1500000
0%
#1510000
1%
#1515000
b0 '
#1520000
b0 !
b10 "
1#
0%
#1525000
0#
#1530000
b10 !
b0 "
1%
#1540000
0%
#1550000
1%
#1560000
0%
#1565000
b1 '
#1570000
b0 !
b10 "
1#
1%
#1575000
0#
#1580000
0%
#1590000
b10 !
b1 "
1%
#1600000
0%
#1610000
1%
#1615000
b10 '
#1620000
b10 "
1#
0%
#1625000
0#
#1630000
1%
#1640000
0%
#1650000
1%
#1660000
0%
#1665000
b11 '
#1670000
b0 !
b10 "
1#
1%
#1675000
0#
#1680000
0%
#1690000
b10 !
b11 "
1%
#1700000
0%
#1710000
1%
#1720000
0)
0%
#1730000
1%
#1740000
0%
#1750000
1%
#1760000
b0 '
0%
#1765000
b0 !
b10 "
1#
#1770000
0#
1%
#1780000
0%
#1790000
1%
#1800000
0%
#1810000
b1 '
1%
#1815000
1#
#1820000
0#
0%
#1830000
1%
#1840000
0%
#1850000
1%
#1860000
b10 '
0%
#1865000
b10 !
1#
#1870000
0#
1%
#1880000
0%
#1890000
1%
#1900000
0%
#1910000
b11 '
1%
#1915000
b0 !
1#
#1920000
0#
0%
#1930000
1%
#1940000
0%
#1950000
1%
#1960000
0%
b1 $
b100 +
#1965000
1)
#1970000
b10 !
b11 "
1%
#1980000
0%
#1990000
1%
#2000000
0%
#2005000
b0 '
#2010000
b1 !
b10 "
1#
1%
#2015000
0#
#2020000
0%
#2030000
b10 !
b0 "
1%
#2040000
0%
#2050000
1%
#2055000
b1 '
#2060000
b1 !
b10 "
1#
0%
#2065000
0#
#2070000
b10 !
b1 "
1%
#2080000
0%
#2090000
1%
#2100000
0%
#2105000
b10 '
#2110000
b11 !
b10 "
1#
1%
#2115000
0#
#2120000
0%
#2130000
1%
#2140000
0%
#2150000
1%
#2155000
b11 '
#2160000
b1 !
1#
0%
#2165000
0#
#2170000
b10 !
b11 "
1%
#2180000
0%
#2190000
1%
#2200000
0%
#2210000
0)
1%
#2220000
0%
#2230000
1%
#2240000
0%
#2250000
b0 '
1%
#2255000
b1 !
b10 "
1#
#2260000
0#
0%
#2270000
1%
#2280000
0%
#2290000
1%
#2300000
b1 '
0%
#2305000
1#
#2310000
0#
1%
#2320000
0%
#2330000
1%
#2340000
0%
#2350000
b10 '
1%
#2355000
b11 !
1#
#2360000
0#
0%
#2370000
1%
#2380000
0%
#2390000
1%
#2400000
b11 '
0%
#2405000
b1 !
1#
#2410000
0#
1%
#2420000
0%
#2430000
1%
#2440000
0%
#2450000
1%
b0 $
b0 (
b100 *
b101 +
#2455000
1)
#2460000
0%
#2470000
b100 !
b11 "
1%
#2480000
0%
#2490000
1%
#2495000
b0 '
#2500000
b0 !
b10 "
1#
0%
#2505000
0#
#2510000
b100 !
b0 "
1%
#2520000
0%
#2530000
1%
#2540000
0%
#2545000
b1 '
#2550000
b0 !
b10 "
1#
1%
#2555000
0#
#2560000
0%
#2570000
b100 !
b1 "
1%
#2580000
0%
#2590000
1%
#2595000
b10 '
#2600000
b0 !
b10 "
1#
0%
#2605000
0#
#2610000
b100 !
1%
#2620000
0%
#2630000
1%
#2640000
0%
#2645000
b11 '
#2650000
b0 !
b10 "
1#
1%
#2655000
0#
#2660000
0%
#2670000
b100 !
b11 "
1%
#2680000
0%
#2690000
1%
#2700000
0)
0%
#2710000
1%
#2720000
0%
#2730000
1%
#2740000
b0 '
0%
#2745000
b0 !
b10 "
1#
#2750000
0#
1%
#2760000
0%
#2770000
1%
#2780000
0%
#2790000
b1 '
1%
#2795000
1#
#2800000
0#
0%
#2810000
1%
#2820000
0%
#2830000
1%
#2840000
b10 '
0%
#2845000
1#
#2850000
0#
1%
#2860000
0%
#2870000
1%
#2880000
0%
#2890000
b11 '
1%
#2895000
1#
#2900000
0#
0%
#2910000
1%
#2920000
0%
#2930000
1%
#2940000
0%
b10 (
b110 +
#2945000
1)
#2950000
b110 !
b11 "
1%
#2960000
0%
#2970000
1%
#2980000
0%
#2985000
b0 '
#2990000
b0 !
b10 "
1#
1%
#2995000
0#
#3000000
0%
#3010000
b110 !
b0 "
1%
#3020000
0%
#3030000
1%
#3035000
b1 '
#3040000
b0 !
b10 "
1#
0%
#3045000
0#
#3050000
b110 !
b1 "
1%
#3060000
0%
#3070000
1%
#3080000
0%
#3085000
b10 '
#3090000
b10 !
b10 "
1#
1%
#3095000
0#
#3100000
0%
#3110000
b110 !
1%
#3120000
0%
#3130000
1%
#3135000
b11 '
#3140000
b0 !
1#
0%
#3145000
0#
#3150000
b110 !
b11 "
1%
#3160000
0%
#3170000
1%
#3180000
0%
#3190000
0)
1%
#3200000
0%
#3210000
1%
#3220000
0%
#3230000
b0 '
1%
#3235000
b0 !
b10 "
1#
#3240000
0#
0%
#3250000
1%
#3260000
0%
#3270000
1%
#3280000
b1 '
0%
#3285000
1#
#3290000
0#
1%
#3300000
0%
#3310000
1%
#3320000
0%
#3330000
b10 '
1%
#3335000
b10 !
1#
#3340000
0#
0%
#3350000
1%
#3360000
0%
#3370000
1%
#3380000
b11 '
0%
#3385000
b0 !
1#
#3390000
0#
1%
#3400000
0%
#3410000
1%
#3420000
0%
#3430000
1%
b1 $
b0 (
b111 +
#3435000
1)
#3440000
0%
#3450000
b100 !
b11 "
1%
#3460000
0%
#3470000
1%
#3475000
b0 '
#3480000
b1 !
b10 "
1#
0%
#3485000
0#
#3490000
b100 !
b0 "
1%
#3500000
0%
#3510000
1%
#3520000
0%
#3525000
b1 '
#3530000
b1 !
b10 "
1#
1%
#3535000
0#
#3540000
0%
#3550000
b100 !
b1 "
1%
#3560000
0%
#3570000
1%
#3575000
b10 '
#3580000
b1 !
b10 "
1#
0%
#3585000
0#
#3590000
b101 !
1%
#3600000
0%
#3610000
1%
#3620000
0%
#3625000
b11 '
#3630000
b1 !
b10 "
1#
1%
#3635000
0#
#3640000
0%
#3650000
b100 !
b11 "
1%
#3660000
0%
#3670000
1%
#3680000
0)
0%
#3690000
1%
#3700000
0%
#3710000
1%
#3720000
b0 '
0%
#3725000
b1 !
b10 "
1#
#3730000
0#
1%
#3740000
0%
#3750000
1%
#3760000
0%
#3770000
b1 '
1%
#3775000
1#
#3780000
0#
0%
#3790000
1%
#3800000
0%
#3810000
1%
#3820000
b10 '
0%
#3825000
1#
#3830000
0#
1%
#3840000
0%
#3850000
1%
#3860000
0%
#3870000
b11 '
1%
#3875000
1#
#3880000
0#
0%
#3890000
1%
#3900000
0%
#3910000
1%
#3920000
0%
b1000 +
