tests/testfiles/ift/test_cells/shift/shift_ift.v
/* Generated by Yosys 0.20 (git sha1 4fcb95ed087, clang  -fPIC -Os) */

(* dynports =  1  *)
(* cells_not_processed =  1  *)
(* src = "shift.v:1.1-29.10" *)
module m_0(A,A_t, B,B_t, Y,Y_t);
  (* src = "shift.v:24.28-24.34" *)
  wire [1:0] _0_;
  (* src = "shift.v:9.25-9.26" *)
  input [1:0] A;
  wire [1:0] A;
  (* src = "shift.v:10.25-10.26" *)
  input [1:0] B;
  wire [1:0] B;
  (* src = "shift.v:11.26-11.27" *)
  output [1:0] Y;
  wire [1:0] Y;
  
  input wire [31:0] A_t;
  input wire [31:0] B_t;
  output wire [31:0] Y_t;
  assign Y = $signed(B) < 0 ? A << - B : A >> B;
  assign _0_[1] = Y[1];
  assign _0_[0] = Y[0];
  assign Y_t = A_t | B_t;
endmodule

tests/testfiles/ift/test_cells/shift/shift_ift_tb.v
`timescale 1ns/1ps
module shift_tb();
	reg [1:0] A;
	reg [1:0] B;
	wire[1:0] Y;
	
	reg[31:0] A_t;
	reg[31:0] B_t;
	wire[31:0] Y_t;

	reg[63:0] read_data [0:3];
	integer i;
	
	m_0 d1(.A(A),.A_t(A_t),.B(B),.B_t(B_t),.Y(Y),.Y_t(Y_t));


	initial begin 
	$readmemb(`INPUT_FILE_NAME, read_data);
		for(i = 0; i<=3; i+=1) begin
		{ A_t,B_t} = read_data[i]; 
		 #100;
		 A <= 'b00;
		 B <= 'b00;
		 #10;
		 B <= 'b01;
		 #10;
		 B <= 'b10;
		 #10;
		 B <= 'b11;
		 #10;
		 #100;
		 A <= 'b01;
		 B <= 'b00;
		 #10;
		 B <= 'b01;
		 #10;
		 B <= 'b10;
		 #10;
		 B <= 'b11;
		 #10;
		 #100;
		 A <= 'b10;
		 B <= 'b00;
		 #10;
		 B <= 'b01;
		 #10;
		 B <= 'b10;
		 #10;
		 B <= 'b11;
		 #10;
		 #100;
		 A <= 'b11;
		 B <= 'b00;
		 #10;
		 B <= 'b01;
		 #10;
		 B <= 'b10;
		 #10;
		 B <= 'b11;
		 #10;
		 #100;
		 end
		 
		 $finish;
	end
	initial
	begin
		$dumpfile(`DUMP_FILE_NAME);
		//$dumpfile("shift.vcd");  
		$dumpvars(1);		//writing the vcd file
	end
 	
endmodule

tests/testfiles/ift/test_cells/shift/shift_ift.vcd
$date
	Tue Jan 16 14:38:52 2024
$end
$version
	Icarus Verilog
$end
$timescale
	1ps
$end
$scope module shift_tb $end
$var wire 32 ! Y_t [31:0] $end
$var wire 2 " Y [1:0] $end
$var reg 2 # A [1:0] $end
$var reg 32 $ A_t [31:0] $end
$var reg 2 % B [1:0] $end
$var reg 32 & B_t [31:0] $end
$var integer 32 ' i [31:0] $end
$upscope $end
$enddefinitions $end
$comment Show the parameter values. $end
$dumpall
$end
#0
$dumpvars
b0 '
b10 &
bx %
b1 $
bx #
bx "
b11 !
$end
#100000
b0 "
b0 %
b0 #
#110000
b1 %
#120000
b10 %
#130000
b11 %
#240000
b1 "
b0 %
b1 #
#250000
b0 "
b1 %
#260000
b10 %
#270000
b10 "
b11 %
#380000
b0 %
b10 #
#390000
b1 "
b1 %
#400000
b0 "
b10 %
#410000
b11 %
#520000
b11 "
b0 %
b11 #
#530000
b1 "
b1 %
#540000
b0 "
b10 %
#550000
b10 "
b11 %
#660000
b1 !
b0 &
b1 '
#760000
b0 "
b0 %
b0 #
#770000
b1 %
#780000
b10 %
#790000
b11 %
#900000
b1 "
b0 %
b1 #
#910000
b0 "
b1 %
#920000
b10 %
#930000
b10 "
b11 %
#1040000
b0 %
b10 #
#1050000
b1 "
b1 %
#1060000
b0 "
b10 %
#1070000
b11 %
#1180000
b11 "
b0 %
b11 #
#1190000
b1 "
b1 %
#1200000
b0 "
b10 %
#1210000
b10 "
b11 %
#1320000
b10 !
b0 $
b10 &
b10 '
#1420000
b0 "
b0 %
b0 #
#1430000
b1 %
#1440000
b10 %
#1450000
b11 %
#1560000
b1 "
b0 %
b1 #
#1570000
b0 "
b1 %
#1580000
b10 %
#1590000
b10 "
b11 %
#1700000
b0 %
b10 #
#1710000
b1 "
b1 %
#1720000
b0 "
b10 %
#1730000
b11 %
#1840000
b11 "
b0 %
b11 #
#1850000
b1 "
b1 %
#1860000
b0 "
b10 %
#1870000
b10 "
b11 %
#1980000
b0 !
b0 &
b11 '
#2080000
b0 "
b0 %
b0 #
#2090000
b1 %
#2100000
b10 %
#2110000
b11 %
#2220000
b1 "
b0 %
b1 #
#2230000
b0 "
b1 %
#2240000
b10 %
#2250000
b10 "
b11 %
#2360000
b0 %
b10 #
#2370000
b1 "
b1 %
#2380000
b0 "
b10 %
#2390000
b11 %
#2500000
b11 "
b0 %
b11 #
#2510000
b1 "
b1 %
#2520000
b0 "
b10 %
#2530000
b10 "
b11 %
#2640000
b100 '
